Data-Memory/data_memory.v
// 1kb data memory for MIPS microarch

module dataMemory (
    input               clk, rst, writeEnable,
    input      [31 : 0] address, dataWrite,
    output [31 : 0] dataOutput
);
    
    reg [31 : 0] data [1023 : 0];
    integer  i;
    always @(posedge clk, posedge rst) begin
        if(rst)begin
            for(i = 1;i < 1024&&i!=32;i++)
                data[i] <= 0;
            data[32]<= 32'h00000005;                              // $t1 = 0x05;
        end
        else if(writeEnable)   
                data[address] <= dataWrite;
    end

    assign dataOutput = data[address];
endmodule

ALU/alu.v

module ALU(
    input      [31 : 0] SrcA, SrcB,
    input      [2 : 0] ALUControl,
    output reg [31 : 0]ALUResult);

localparam 
add = 3'b010,
xorr= 3'b011,
sub = 3'b110,
andd= 3'b000,
orr = 3'b001, // ignore for now
slt = 3'b111; // ignore for now

always @(*) begin
    case (ALUControl)
        add :  ALUResult = SrcA + SrcB;
        sub :  ALUResult = SrcA - SrcB;
        andd:  ALUResult = SrcA & SrcB;
        xorr:  ALUResult = SrcA ^ SrcB;
        default: ALUResult = 0;
    endcase
end


endmodule

Register-File/register_file.v
module registerFile (
    input rst, clk, writeEnable,
    input [31 : 0] dataWrite, 
    input [4 : 0] addressWrite, addressA, addressB,
    output reg [31 : 0] dataA, dataB
);
    integer  i;
    reg [31 : 0] registerFileData [31 : 0];


    always @(posedge clk, posedge rst) begin
        if(rst) begin
            for(i = 0; i < 32; i++)
                registerFileData[i] <= 0;
        end
        else if(writeEnable)
            registerFileData[addressWrite] = dataWrite;
    end



    always@(*)begin
        dataA = registerFileData[addressA];
        dataB = registerFileData[addressB];
    end
    wire [31 : 0] testRegister; assign testRegister = registerFileData[10];
endmodule

Instruction-Memory/instruction_memory.v
// 1kb data memory for MIPS microarch

module instructionMemory (
    input           clk, rst,
    input  [31 : 0] address,
    output [31 : 0] instruction
);
    reg [31 : 0] data [1023 : 0];
    integer  i;
    always @(posedge clk, posedge rst) begin
        if(rst)begin
            for(i = 1;i < 1024;i++)
                data[i] <= 0;
            data[0] <= 32'h8C0A0020;                              // lw $t1, 32($0), t1 = 5
        end
    end

    // data[1] <= 32'b000100_01010_01010_0000000000000011;   // beq $t1, $t1, add(5)
    // data[5] <= 32'b000000_10100_01010_01010_00000_100000; // add $t1, $t1, $some other register

    assign instruction = data[address];

endmodule

data_path.v
`include "Instruction-Memory/instruction_memory.v"
`include "Data-Memory/data_memory.v"
`include "ALU/alu.v"
`include "Register-File/register_file.v"
`include "Program-Counter/program_counter.v"

module dataPath(
    input              rst, clk,
    // cu
    input              regWrite, regDst, memWrite, mem2Reg, aluSrcB, pcSrc,
    input      [2 : 0] aluControl,
    // for control/hazard
    output     [5 : 0] opcode, funct,
    output             eq,

    // hazard inputs
    input      [1 : 0] fad, fbd,
    input              flush
);
    // control outputs
    assign funct = instr[5 : 0];
    assign opcode = instr[31 : 26];

    // fetch stage
    wire [31 : 0]addToPC;   
    assign  addToPC = pcSrc ? 4 : immShiftedD; // why this wrong 
    reg [31 : 0] PC; always@(posedge clk, posedge rst)if(rst)PC <= 0; else PC <= PC + addToPC;

    wire [31 : 0] instr;
    instructionMemory IM(.clk(clk), .rst(rst), .instruction(instr), .address(PC));

    // decode stage
    // decode flop
    reg [31 : 0] instrD;
    always @(posedge clk, posedge flush, posedge rst)if((flush & clk) | rst)instrD <= 0; else instrD <= instr;

    wire [4 : 0] rsD, rtD, rdD; assign rsD = instrD[25 : 21]; assign rtD = instrD[20 : 16]; assign rdD = instrD[15 : 11];
    wire [31 : 0] rsDataD, rtDataD;
    reg  [31 : 0] rsDataFD, rtDataFD;

    registerFile RF(.rst(rst), .clk(clk), .writeEnable(regWriteWB), .addressWrite(writeRegWB),
                .dataWrite(writeRegData), .addressA(rsD), .addressB(rtD), .dataA(rsDataD),
                .dataB(rtDataD));
    wire [31 : 0] immD; assign immD = {instrD[15]?16'hffff : 16'h0000 , instrD[15 : 0]};
    wire [31 : 0] immShiftedD = immD << 2;
    assign eq = &(~(rsDataFD ^ rtDataFD));
    // forward muxes
    always @(*) begin
        case (fad)
            0 : rsDataFD = rsDataD;     
            1 : rsDataFD = aluOutE; 
            2 : rsDataFD = memDataM;
            3 : rsDataFD = aluOutM;
            default: rsDataFD = 0;
        endcase
        case (fbd)
            0 : rtDataFD = rtDataD;     
            1 : rtDataFD = aluOutE; 
            2 : rtDataFD = memDataM;
            3 : rtDataFD = aluOutM;
            default: rtDataFD = 0;
        endcase
    end




    // execute flop
    reg [31 : 0] rsDataE, rtDataE, immE;
    reg [5 : 0] rsE, rtE, rdE;
    reg regDstE, aluSrcBE, regWriteE, mem2RegE, memWriteE;
    reg [2 : 0] aluControlE;
    always @(posedge clk, posedge rst)begin
        if(rst)begin
            memWriteE   <= 0;
            regWriteE   <= 0;
        end else begin
            rsDataE     <= rsDataFD;
            rtDataE     <= rtDataFD;
            immE        <= immD;
            rsE         <= rsD;
            rtE         <= rtD;
            rdE         <= rdD;

            memWriteE   <= memWrite;
            mem2RegE    <= mem2Reg;
            regDstE     <= regDst;
            aluSrcBE    <= aluSrcB;
            aluControlE <= aluControl;
            regWriteE   <= regWrite;
        end
    end
    // execute stage
    wire [31 : 0] operand2; assign operand2 = aluSrcBE?rtDataE : immE;
    wire [31 : 0] aluOutE;
    ALU a(.SrcA(rsDataE), .SrcB(operand2), .ALUControl(aluControlE), .ALUResult(aluOutE));
    wire [4 : 0] writeRegE; assign writeRegE = regDst?rtE:rdE;




    // memory read
    reg [31 : 0] aluOutM, rtDataM;
    reg regWriteM, mem2RegM, memWriteM;
    reg [4 : 0] writeRegM;
    always @(posedge clk, posedge rst)begin
        if(rst)begin
            memWriteE   <= 0;
            regWriteE   <= 0;
        end else begin
            aluOutM <= aluOutE;
            rtDataM  <= rtDataE;
            writeRegM<= writeRegE;
            regWriteM<= regWriteE;
            mem2RegM  <= mem2RegE;
            memWriteM<= memWriteE;
        end
    end

    wire [31 : 0] memDataM;    
    dataMemory DM(.clk(clk), .rst(rst), .writeEnable(memWriteM), .address(aluOutM), .dataWrite(rtDataM),
                  .dataOutput(memDataM));





    // writeback flop
    reg [31 : 0] memDataWB, aluOutWB;
    reg [4 : 0] writeRegWB;
    reg regWriteWB, mem2RegWB;
    always @(posedge clk, posedge rst)begin
        if(rst)begin
            memWriteE   <= 0;
            regWriteE   <= 0;
        end else begin
            regWriteWB <= regWriteM;
            memDataWB  <= memDataM;
            aluOutWB   <= aluOutM;
            writeRegWB <= writeRegM;
            mem2RegWB  <= mem2RegM;
        end
    end

    wire [31 : 0] writeRegData; assign writeRegData = mem2RegWB? aluOutWB : memDataWB;
endmodule

// Register file nomenclature
    // writeReg       => address of reg to write
    // writeRegData => data to be written
    // regWrite       => control signal to write

dp_testbench.v
`include "data_path.v"
`timescale 1ns/1ps

module tb;


    reg clk, rst, regWrite, regDst, memWrite, mem2Reg, aluSrcB, pcSrc, flush;
    reg [2 : 0] aluControl;
    reg [1 : 0]  fad, fbd;

    always #10 clk ^= 1;

    dataPath dp(.rst(rst), .clk(clk),.regWrite(regWrite), .regDst(regDst), .memWrite(memWrite),
                .mem2Reg(mem2Reg), .aluSrcB(aluSrcB), .pcSrc(pcSrc), .aluControl(aluControl), 
                .fad(fad), .fbd(fbd), .flush(flush));

    initial begin
        $dumpfile("dp_testbench.vcd");
        $dumpvars(0, tb);
        flush = 0;

        clk = 0;
        // resetting pc
        pcSrc = 0;

        @(negedge clk);
        rst = 1;
        #5;
        rst = 0;

        @(negedge clk);
        regWrite = 1;
        memWrite = 0;
        fad = 0; 
        fbd = 0;
        aluSrcB = 0;
        regDst = 0;
        mem2Reg = 1;

        #250;
        $finish;
    end


endmodule

dp_testbench.vcd
$date
	Fri Jul 12 17:50:48 2024
$end
$version
	Icarus Verilog
$end
$timescale
	1ps
$end
$scope module tb $end
$var reg 3 ! aluControl [2:0] $end
$var reg 1 " aluSrcB $end
$var reg 1 # clk $end
$var reg 2 $ fad [1:0] $end
$var reg 2 % fbd [1:0] $end
$var reg 1 & flush $end
$var reg 1 ' mem2Reg $end
$var reg 1 ( memWrite $end
$var reg 1 ) pcSrc $end
$var reg 1 * regDst $end
$var reg 1 + regWrite $end
$var reg 1 , rst $end
$scope module dp $end
$var wire 3 - aluControl [2:0] $end
$var wire 1 " aluSrcB $end
$var wire 1 # clk $end
$var wire 2 . fad [1:0] $end
$var wire 2 / fbd [1:0] $end
$var wire 1 & flush $end
$var wire 1 ' mem2Reg $end
$var wire 1 ( memWrite $end
$var wire 1 ) pcSrc $end
$var wire 1 * regDst $end
$var wire 1 + regWrite $end
$var wire 1 , rst $end
$var wire 5 0 writeRegE [4:0] $end
$var wire 32 1 writeRegData [31:0] $end
$var wire 32 2 rtDataD [31:0] $end
$var wire 5 3 rtD [4:0] $end
$var wire 32 4 rsDataD [31:0] $end
$var wire 5 5 rsD [4:0] $end
$var wire 5 6 rdD [4:0] $end
$var wire 32 7 operand2 [31:0] $end
$var wire 6 8 opcode [5:0] $end
$var wire 32 9 memDataM [31:0] $end
$var wire 32 : instr [31:0] $end
$var wire 32 ; immShiftedD [31:0] $end
$var wire 32 < immD [31:0] $end
$var wire 6 = funct [5:0] $end
$var wire 1 > eq $end
$var wire 32 ? aluOutE [31:0] $end
$var wire 32 @ addToPC [31:0] $end
$var reg 32 A PC [31:0] $end
$var reg 3 B aluControlE [2:0] $end
$var reg 32 C aluOutM [31:0] $end
$var reg 32 D aluOutWB [31:0] $end
$var reg 1 E aluSrcBE $end
$var reg 32 F immE [31:0] $end
$var reg 32 G instrD [31:0] $end
$var reg 1 H mem2RegE $end
$var reg 1 I mem2RegM $end
$var reg 1 J mem2RegWB $end
$var reg 32 K memDataWB [31:0] $end
$var reg 1 L memWriteE $end
$var reg 1 M memWriteM $end
$var reg 6 N rdE [5:0] $end
$var reg 1 O regDstE $end
$var reg 1 P regWriteE $end
$var reg 1 Q regWriteM $end
$var reg 1 R regWriteWB $end
$var reg 32 S rsDataE [31:0] $end
$var reg 32 T rsDataFD [31:0] $end
$var reg 6 U rsE [5:0] $end
$var reg 32 V rtDataE [31:0] $end
$var reg 32 W rtDataFD [31:0] $end
$var reg 32 X rtDataM [31:0] $end
$var reg 6 Y rtE [5:0] $end
$var reg 5 Z writeRegM [4:0] $end
$var reg 5 [ writeRegWB [4:0] $end
$scope module DM $end
$var wire 32 \ address [31:0] $end
$var wire 1 # clk $end
$var wire 32 ] dataOutput [31:0] $end
$var wire 32 ^ dataWrite [31:0] $end
$var wire 1 , rst $end
$var wire 1 M writeEnable $end
$var integer 32 _ i [31:0] $end
$upscope $end
$scope module IM $end
$var wire 32 ` address [31:0] $end
$var wire 1 # clk $end
$var wire 32 a instruction [31:0] $end
$var wire 1 , rst $end
$var integer 32 b i [31:0] $end
$upscope $end
$scope module RF $end
$var wire 5 c addressA [4:0] $end
$var wire 5 d addressB [4:0] $end
$var wire 5 e addressWrite [4:0] $end
$var wire 1 # clk $end
$var wire 32 f dataWrite [31:0] $end
$var wire 1 , rst $end
$var wire 32 g testRegister [31:0] $end
$var wire 1 R writeEnable $end
$var reg 32 h dataA [31:0] $end
$var reg 32 i dataB [31:0] $end
$var integer 32 j i [31:0] $end
$upscope $end
$scope module a $end
$var wire 3 k ALUControl [2:0] $end
$var wire 32 l SrcA [31:0] $end
$var wire 32 m SrcB [31:0] $end
$var parameter 3 n add $end
$var parameter 3 o andd $end
$var parameter 3 p orr $end
$var parameter 3 q slt $end
$var parameter 3 r sub $end
$var reg 32 s ALUResult [31:0] $end
$upscope $end
$upscope $end
$upscope $end
$enddefinitions $end
$comment Show the parameter values. $end
$dumpall
b110 r
b111 q
b1 p
b0 o
b10 n
$end
#0
$dumpvars
bx s
bx m
bx l
bx k
bx j
bx i
bx h
bx g
bx f
bx e
bx d
bx c
bx b
bx a
bx `
bx _
bx ^
bx ]
bx \
bx [
bx Z
bx Y
bx X
bx W
bx V
bx U
bx T
bx S
xR
xQ
xP
xO
bx N
xM
xL
bx K
xJ
xI
xH
bx G
bx F
xE
bx D
bx C
bx B
bx A
bx00 @
bx ?
x>
bx =
bx <
bx00 ;
bx :
bx 9
bx 8
bx 7
bx 6
bx 5
bx 4
bx 3
bx 2
bx 1
bx 0
bx /
bx .
bx -
x,
x+
x*
0)
x(
x'
0&
bx %
bx $
0#
x"
bx !
$end
#10000
b0xxxxx N
b0xxxxx Y
b0xxxxx U
1#
#20000
1>
b0 @
b0 W
b0 T
b0 ;
b100011 8
b100000 =
b0 2
b0 i
b0 4
b0 h
b0 5
b0 c
b0 3
b0 d
b0 6
b0 <
0P
0L
b10001100000010100000000000100000 :
b10001100000010100000000000100000 a
b0 A
b0 `
b0 g
b0 G
b100000 _
b100000 j
b10000000000 b
1,
0#
#25000
0,
#30000
b10000000 @
b0 0
b10000000 ;
b0 7
b0 m
b0 ?
b0 s
b1010 3
b1010 d
b100000 <
xP
xL
b0 N
b0 Y
b0 U
b0 F
b0 V
b0 S
b0 l
0M
0Q
b10001100000010100000000000100000 G
1#
#40000
1'
0*
0"
b0 %
b0 /
b0 $
b0 .
0(
1+
0#
#50000
b100000 7
b100000 m
b0 8
b0 =
0R
xM
xQ
b0 Z
b0 X
b0 ^
b0 C
b0 \
1P
0E
0O
1H
0L
b1010 Y
b100000 F
b0 :
b0 a
b10000000 A
b10000000 `
1#
#60000
0#
#70000
b0 @
b0 ;
b0 3
b0 d
b0 <
b100000000 A
b100000000 `
0M
1I
1Q
b0 [
b0 e
b0 D
xR
b0 G
1#
#80000
0#
#90000
b0 1
b0 f
b0 7
b0 m
1J
1R
b0 Y
b0 F
1#
