Data-Memory/data_memory.v
// 1kb data memory for MIPS microarch

module dataMemory (
    input               clk, rst, writeEnable,
    input      [31 : 0] address, dataWrite,
    output [31 : 0] dataOutput
);
    
    reg [31 : 0] data [1023 : 0];
    integer  i;
    always @(posedge clk, posedge rst) begin
        if(rst)begin
            data[32]<= 2;
            data[33]<= 0;
            data[34]<= 64;
            data[35]<= 4;
        end
        else if(writeEnable)   
                data[address] <= dataWrite;
    end

    assign dataOutput = data[address];
endmodule

ALU/alu.v

module ALU(
    input      [31 : 0] SrcA, SrcB,
    input      [2 : 0] ALUControl,
    output reg [31 : 0]ALUResult);

localparam 
add = 3'b010,
xorr= 3'b011,
sub = 3'b110,
andd= 3'b000,
orr = 3'b001, // ignore for now
slt = 3'b111; // ignore for now

always @(*) begin
    case (ALUControl)
        add :  ALUResult = SrcA + SrcB;
        sub :  ALUResult = SrcA - SrcB;
        andd:  ALUResult = SrcA & SrcB;
        xorr:  ALUResult = SrcA ^ SrcB;
        default: ALUResult = 0;
    endcase
end


endmodule

Register-File/register_file.v
module registerFile (
    input rst, clk, writeEnable,
    input [31 : 0] dataWrite, 
    input [4 : 0] addressWrite, addressA, addressB,
    output reg [31 : 0] dataA, dataB
);
    integer  i;
    reg [31 : 0] registerFileData [31 : 0];


    always @(posedge clk, posedge rst) begin
        if(rst) begin
            for(i = 0; i < 32; i++)
                registerFileData[i] <= 0;
        end
        else if(writeEnable)
            registerFileData[addressWrite] = dataWrite;
    end



    always@(*)begin
        dataA = registerFileData[addressA];
        dataB = registerFileData[addressB];
    end
    wire [31 : 0] testRegister; assign testRegister = registerFileData[10];
endmodule

Instruction-Memory/instruction_memory.v
// 1kb data memory for MIPS microarch

module instructionMemory (
    input           clk, rst,
    input  [31 : 0] address,
    output [31 : 0] instruction
);
    reg [31 : 0] data [1023 : 0];
    integer  i;
    always @(posedge clk, posedge rst) begin
        if(rst)begin
            for(i = 2;i < 1024;i++)
                data[i] <= 0;
            data[0] <= 32'b000000_10100_01010_01010_00000_100000; // add $t1, $t1, $some other register
            data[1] <= 32'b000000_10100_01010_01010_00000_100000; // add $t1, $t1, $some other register
        end
    end

    // data[0] <= 32'h8C0A0020;                              // lw $t1, 32($0), t1 = 5
    // data[1] <= 32'h8C0A0021;                              // lw $t1, 33($0), t1 = 6
    // data[1] <= 32'b000100_01010_01010_0000000000000011;   // beq $t1, $t1, add(5)

    assign instruction = data[address];

endmodule

data_path.v
`include "Instruction-Memory/instruction_memory.v"
`include "Data-Memory/data_memory.v"
`include "ALU/alu.v"
`include "Register-File/register_file.v"
`include "Program-Counter/program_counter.v"

module dataPath(
    input              rst, clk,
    // cu
    input              regWrite, regDst, memWrite, mem2Reg, aluSrcB, pcSrc,
    input      [2 : 0] aluControl,
    // for control/hazard
    output     [5 : 0] opcode, funct,
    output             eq,

    // hazard inputs
    input      [1 : 0] fad, fbd,
    input              flush
);
    // control outputs
    assign funct = instr[5 : 0];
    assign opcode = instr[31 : 26];

    // fetch stage
    reg [31 : 0] PC; always@(posedge clk, posedge rst)if(rst)PC <= 0; else PC <= PC + (pcSrc ? immShiftedD : 1);
    wire [31 : 0] instr;
    instructionMemory IM(.clk(clk), .rst(rst), .instruction(instr), .address(PC));

    // decode stage
    // decode flop
    reg [31 : 0] instrD;
    always @(posedge clk, posedge flush, posedge rst)if((flush & clk) | rst)instrD <= 0; else instrD <= instr;

    wire [4 : 0] rsD, rtD, rdD; assign rsD = instrD[25 : 21]; assign rtD = instrD[20 : 16]; assign rdD = instrD[15 : 11];
    wire [31 : 0] rsDataD, rtDataD;
    reg  [31 : 0] rsDataFD, rtDataFD;

    registerFile RF(.rst(rst), .clk(clk), .writeEnable(regWriteWB), .addressWrite(writeRegWB),
                .dataWrite(writeRegData), .addressA(rsD), .addressB(rtD), .dataA(rsDataD),
                .dataB(rtDataD));
    wire [31 : 0] immD; assign immD = {instrD[15]?16'hffff : 16'h0000 , instrD[15 : 0]};
    wire [31 : 0] immShiftedD = immD;
    assign eq = &(~(rsDataFD ^ rtDataFD));
    // forward muxes
    always @(*) begin
        case (fad)
            0 : rsDataFD = rsDataD;     
            1 : rsDataFD = aluOutE; 
            2 : rsDataFD = memDataM;
            3 : rsDataFD = aluOutM;
            default: rsDataFD = 0;
        endcase
        case (fbd)
            0 : rtDataFD = rtDataD;     
            1 : rtDataFD = aluOutE; 
            2 : rtDataFD = memDataM;
            3 : rtDataFD = aluOutM;
            default: rtDataFD = 0;
        endcase
    end




    // execute flop
    reg [31 : 0] rsDataE, rtDataE, immE;
    reg [5 : 0] rsE, rtE, rdE;
    reg regDstE, aluSrcBE, regWriteE, mem2RegE, memWriteE;
    reg [2 : 0] aluControlE;
    always @(posedge clk, posedge rst)begin
        if(rst)begin
            memWriteE   <= 0;
            regWriteE   <= 0;
        end else begin
            rsDataE     <= rsDataFD;
            rtDataE     <= rtDataFD;
            immE        <= immD;
            rsE         <= rsD;
            rtE         <= rtD;
            rdE         <= rdD;

            memWriteE   <= memWrite;
            mem2RegE    <= mem2Reg;
            regDstE     <= regDst;
            aluSrcBE    <= aluSrcB;
            aluControlE <= aluControl;
            regWriteE   <= regWrite;
        end
    end
    // execute stage
    wire [31 : 0] operand2; assign operand2 = aluSrcBE?immE : rtDataE;
    wire [31 : 0] aluOutE;
    ALU a(.SrcA(rsDataE), .SrcB(operand2), .ALUControl(aluControlE), .ALUResult(aluOutE));
    wire [4 : 0] writeRegE; assign writeRegE = regDstE?rdE:rtE;




    // memory read
    reg [31 : 0] aluOutM, rtDataM;
    reg regWriteM, mem2RegM, memWriteM;
    reg [4 : 0] writeRegM;
    always @(posedge clk, posedge rst)begin
        if(rst)begin
            memWriteE   <= 0;
            regWriteE   <= 0;
        end else begin
            aluOutM <= aluOutE;
            rtDataM  <= rtDataE;
            writeRegM<= writeRegE;
            regWriteM<= regWriteE;
            mem2RegM  <= mem2RegE;
            memWriteM<= memWriteE;
        end
    end

    wire [31 : 0] memDataM;    
    dataMemory DM(.clk(clk), .rst(rst), .writeEnable(memWriteM), .address(aluOutM), .dataWrite(rtDataM),
                  .dataOutput(memDataM));





    // writeback flop
    reg [31 : 0] memDataWB, aluOutWB;
    reg [4 : 0] writeRegWB;
    reg regWriteWB, mem2RegWB;
    always @(posedge clk, posedge rst)begin
        if(rst)begin
            memWriteE   <= 0;
            regWriteE   <= 0;
        end else begin
            regWriteWB <= regWriteM;
            memDataWB  <= memDataM;
            aluOutWB   <= aluOutM;
            writeRegWB <= writeRegM;
            mem2RegWB  <= mem2RegM;
        end
    end

    wire [31 : 0] writeRegData; assign writeRegData = mem2RegWB? memDataWB : aluOutWB;
endmodule

// Register file nomenclature
    // writeReg       => address of reg to write
    // writeRegData => data to be written
    // regWrite       => control signal to write

dp_testbench.v
`include "data_path.v"
`timescale 1ns/1ps

module tb;


    reg clk, rst, regWrite, regDst, memWrite, mem2Reg, aluSrcB, pcSrc, flush;
    reg [2 : 0] aluControl;
    reg [1 : 0]  fad, fbd;

    always #10 clk ^= 1;

    dataPath dp(.rst(rst), .clk(clk),.regWrite(regWrite), .regDst(regDst), .memWrite(memWrite),
                .mem2Reg(mem2Reg), .aluSrcB(aluSrcB), .pcSrc(pcSrc), .aluControl(aluControl), 
                .fad(fad), .fbd(fbd), .flush(flush));

    initial begin
        $dumpfile("dp_testbench.vcd");
        $dumpvars(0, tb);
        flush = 0;

        aluControl = 2;
        clk = 0;
        // resetting pc
        pcSrc = 0;

        @(negedge clk);
        rst = 1;
        #5;
        rst = 0;

        @(negedge clk);
        regWrite = 1;
        memWrite = 0;
        fad = 0; 
        fbd = 0;
        aluSrcB = 0;
        regDst = 1;
        mem2Reg = 0;

        @(negedge clk);
        regWrite = 1;
        memWrite = 0;
        fad = 0; 
        fbd = 1;
        aluSrcB = 0;
        regDst = 1;
        mem2Reg = 0;

        #400;
        $finish;
    end


endmodule

dp_testbench.vcd
$date
	Fri Jul 12 19:31:41 2024
$end
$version
	Icarus Verilog
$end
$timescale
	1ps
$end
$scope module tb $end
$var reg 3 ! aluControl [2:0] $end
$var reg 1 " aluSrcB $end
$var reg 1 # clk $end
$var reg 2 $ fad [1:0] $end
$var reg 2 % fbd [1:0] $end
$var reg 1 & flush $end
$var reg 1 ' mem2Reg $end
$var reg 1 ( memWrite $end
$var reg 1 ) pcSrc $end
$var reg 1 * regDst $end
$var reg 1 + regWrite $end
$var reg 1 , rst $end
$scope module dp $end
$var wire 3 - aluControl [2:0] $end
$var wire 1 " aluSrcB $end
$var wire 1 # clk $end
$var wire 2 . fad [1:0] $end
$var wire 2 / fbd [1:0] $end
$var wire 1 & flush $end
$var wire 32 0 immShiftedD [31:0] $end
$var wire 1 ' mem2Reg $end
$var wire 1 ( memWrite $end
$var wire 1 ) pcSrc $end
$var wire 1 * regDst $end
$var wire 1 + regWrite $end
$var wire 1 , rst $end
$var wire 5 1 writeRegE [4:0] $end
$var wire 32 2 writeRegData [31:0] $end
$var wire 32 3 rtDataD [31:0] $end
$var wire 5 4 rtD [4:0] $end
$var wire 32 5 rsDataD [31:0] $end
$var wire 5 6 rsD [4:0] $end
$var wire 5 7 rdD [4:0] $end
$var wire 32 8 operand2 [31:0] $end
$var wire 6 9 opcode [5:0] $end
$var wire 32 : memDataM [31:0] $end
$var wire 32 ; instr [31:0] $end
$var wire 32 < immD [31:0] $end
$var wire 6 = funct [5:0] $end
$var wire 1 > eq $end
$var wire 32 ? aluOutE [31:0] $end
$var reg 32 @ PC [31:0] $end
$var reg 3 A aluControlE [2:0] $end
$var reg 32 B aluOutM [31:0] $end
$var reg 32 C aluOutWB [31:0] $end
$var reg 1 D aluSrcBE $end
$var reg 32 E immE [31:0] $end
$var reg 32 F instrD [31:0] $end
$var reg 1 G mem2RegE $end
$var reg 1 H mem2RegM $end
$var reg 1 I mem2RegWB $end
$var reg 32 J memDataWB [31:0] $end
$var reg 1 K memWriteE $end
$var reg 1 L memWriteM $end
$var reg 6 M rdE [5:0] $end
$var reg 1 N regDstE $end
$var reg 1 O regWriteE $end
$var reg 1 P regWriteM $end
$var reg 1 Q regWriteWB $end
$var reg 32 R rsDataE [31:0] $end
$var reg 32 S rsDataFD [31:0] $end
$var reg 6 T rsE [5:0] $end
$var reg 32 U rtDataE [31:0] $end
$var reg 32 V rtDataFD [31:0] $end
$var reg 32 W rtDataM [31:0] $end
$var reg 6 X rtE [5:0] $end
$var reg 5 Y writeRegM [4:0] $end
$var reg 5 Z writeRegWB [4:0] $end
$scope module DM $end
$var wire 32 [ address [31:0] $end
$var wire 1 # clk $end
$var wire 32 \ dataOutput [31:0] $end
$var wire 32 ] dataWrite [31:0] $end
$var wire 1 , rst $end
$var wire 1 L writeEnable $end
$var integer 32 ^ i [31:0] $end
$upscope $end
$scope module IM $end
$var wire 32 _ address [31:0] $end
$var wire 1 # clk $end
$var wire 32 ` instruction [31:0] $end
$var wire 1 , rst $end
$var integer 32 a i [31:0] $end
$upscope $end
$scope module RF $end
$var wire 5 b addressA [4:0] $end
$var wire 5 c addressB [4:0] $end
$var wire 5 d addressWrite [4:0] $end
$var wire 1 # clk $end
$var wire 32 e dataWrite [31:0] $end
$var wire 1 , rst $end
$var wire 32 f testRegister [31:0] $end
$var wire 1 Q writeEnable $end
$var reg 32 g dataA [31:0] $end
$var reg 32 h dataB [31:0] $end
$var integer 32 i i [31:0] $end
$upscope $end
$scope module a $end
$var wire 3 j ALUControl [2:0] $end
$var wire 32 k SrcA [31:0] $end
$var wire 32 l SrcB [31:0] $end
$var parameter 3 m add $end
$var parameter 3 n andd $end
$var parameter 3 o orr $end
$var parameter 3 p slt $end
$var parameter 3 q sub $end
$var reg 32 r ALUResult [31:0] $end
$upscope $end
$upscope $end
$upscope $end
$enddefinitions $end
$comment Show the parameter values. $end
$dumpall
b110 q
b111 p
b1 o
b0 n
b10 m
$end
#0
$dumpvars
bx r
bx l
bx k
bx j
bx i
bx h
bx g
bx f
bx e
bx d
bx c
bx b
bx a
bx `
bx _
bx ^
bx ]
bx \
bx [
bx Z
bx Y
bx X
bx W
bx V
bx U
bx T
bx S
bx R
xQ
xP
xO
xN
bx M
xL
xK
bx J
xI
xH
xG
bx F
bx E
xD
bx C
bx B
bx A
bx @
bx ?
x>
bx =
bx <
bx ;
bx :
bx 9
bx 8
bx 7
bx 6
bx 5
bx 4
bx 3
bx 2
bx 1
bx 0
bx /
bx .
b10 -
x,
x+
x*
0)
x(
x'
0&
bx %
bx $
0#
x"
b10 !
$end
#10000
b10 A
b10 j
b0xxxxx M
b0xxxxx X
b0xxxxx T
1#
#20000
1>
b0 V
b0 S
b0 9
b100000 =
b0 3
b0 h
b0 5
b0 g
b0 6
b0 b
b0 4
b0 c
b0 7
b0 0
b0 <
0O
0K
b10100010100101000000100000 ;
b10100010100101000000100000 `
b0 @
b0 _
b0 F
b100000 ^
b101 f
b1010 i
b10000000000 a
1,
0#
#25000
0,
#30000
b0 1
b0 ?
b0 r
b101 3
b101 h
b101 5
b101 g
b0 8
b0 l
b10100 6
b10100 b
b1010 4
b1010 c
b1010 7
b101000000100000 0
b101000000100000 <
b1 @
b1 _
xO
xK
b0 M
b0 X
b0 T
b0 E
b0 U
b0 R
b0 k
0L
0P
b10100010100101000000100000 F
1#
#40000
b101 V
b101 S
0'
1*
0"
b0 %
b0 /
b0 $
b0 .
0(
1+
0#
#50000
b1010 1
b101 8
b101 l
b1010 ?
b1010 r
b0 =
0Q
xL
xP
b0 Y
b0 W
b0 ]
b0 B
b0 [
1O
0D
1N
0G
0K
b1010 M
b1010 X
b10100 T
b101000000100000 E
b101 U
b101 R
b101 k
b0 ;
b0 `
b10 @
b10 _
1#
#60000
0>
b1010 V
b1 %
b1 /
0#
#70000
b1111 V
b0 S
b1111 ?
b1111 r
b0 3
b0 h
b0 5
b0 g
b1010 8
b1010 l
b0 6
b0 b
b0 4
b0 c
b0 7
b0 0
b0 <
b11 @
b11 _
b1010 U
0L
0H
1P
b1010 Y
b101 W
b101 ]
b0 :
b0 \
b1010 B
b1010 [
b0 Z
b0 d
b0 C
xQ
b0 F
1#
#80000
0#
#90000
b0 1
b1010 2
b1010 e
b1111 V
b1111 8
b1111 l
b1111 ?
b1111 r
0I
b1010 Z
b1010 d
b1010 C
b0 J
1Q
b1010 W
b1010 ]
b1111 B
b1111 [
b0 M
b0 X
b0 T
b0 E
b1111 U
b0 R
b0 k
b100 @
b100 _
1#
#100000
0#
#110000
b1111 2
b1111 e
b101 @
b101 _
b0 Y
b1111 W
b1111 ]
b1111 C
b1010 f
1#
#120000
0#
#130000
b0 Z
b0 d
b110 @
b110 _
b1111 f
1#
#140000
0#
#150000
b111 @
b111 _
1>
b1111 S
b1111 3
b1111 h
b1111 5
b1111 g
1#
#160000
0#
#170000
0>
b11110 V
b11110 ?
b11110 r
b1111 R
b1111 k
b1000 @
b1000 _
1#
#180000
0#
#190000
b101101 V
b101101 ?
b101101 r
b11110 8
b11110 l
b1001 @
b1001 _
b11110 U
b11110 B
b11110 [
1#
#200000
0#
#210000
b111100 V
b111100 ?
b111100 r
b11110 2
b11110 e
b101101 8
b101101 l
b11110 C
b11110 W
b11110 ]
bx :
bx \
b101101 B
b101101 [
b101101 U
b1010 @
b1010 _
1#
#220000
0#
#230000
b1001011 V
b1001011 ?
b1001011 r
b111100 8
b111100 l
b101101 2
b101101 e
b1011 @
b1011 _
b111100 U
b101101 W
b101101 ]
b111100 B
b111100 [
b101101 C
bx J
b11110 S
b11110 3
b11110 h
b11110 5
b11110 g
1#
#240000
0#
#250000
b111100 2
b111100 e
b1101001 V
b1001011 8
b1001011 l
b1101001 ?
b1101001 r
b111100 C
b111100 W
b111100 ]
b1001011 B
b1001011 [
b1001011 U
b11110 R
b11110 k
b1100 @
b1100 _
b101101 S
b101101 3
b101101 h
b101101 5
b101101 g
1#
#260000
0#
#270000
b10010110 V
b1101001 8
b1101001 l
b10010110 ?
b10010110 r
b1001011 2
b1001011 e
b1101 @
b1101 _
b1101001 U
b101101 R
b101101 k
b1001011 W
b1001011 ]
b1101001 B
b1101001 [
b1001011 C
b111100 S
b111100 3
b111100 h
b111100 5
b111100 g
1#
#280000
0#
#290000
b1101001 2
b1101001 e
b11010010 V
b10010110 8
b10010110 l
b11010010 ?
b11010010 r
b1101001 C
b1101001 W
b1101001 ]
b10010110 B
b10010110 [
b10010110 U
b111100 R
b111100 k
b1110 @
b1110 _
b1001011 S
b1001011 3
b1001011 h
b1001011 5
b1001011 g
1#
#300000
0#
#310000
b100011101 V
b11010010 8
b11010010 l
b100011101 ?
b100011101 r
b10010110 2
b10010110 e
b1111 @
b1111 _
b11010010 U
b1001011 R
b1001011 k
b10010110 W
b10010110 ]
b11010010 B
b11010010 [
b10010110 C
b1101001 S
b1101001 3
b1101001 h
b1101001 5
b1101001 g
1#
#320000
0#
#330000
b11010010 2
b11010010 e
b110000110 V
b100011101 8
b100011101 l
b110000110 ?
b110000110 r
b11010010 C
b11010010 W
b11010010 ]
b100011101 B
b100011101 [
b100011101 U
b1101001 R
b1101001 k
b10000 @
b10000 _
b10010110 S
b10010110 3
b10010110 h
b10010110 5
b10010110 g
1#
#340000
0#
#350000
b1000011100 V
b110000110 8
b110000110 l
b1000011100 ?
b1000011100 r
b100011101 2
b100011101 e
b10001 @
b10001 _
b110000110 U
b10010110 R
b10010110 k
b100011101 W
b100011101 ]
b110000110 B
b110000110 [
b100011101 C
b11010010 S
b11010010 3
b11010010 h
b11010010 5
b11010010 g
1#
#360000
0#
#370000
b110000110 2
b110000110 e
b1011101110 V
b1000011100 8
b1000011100 l
b1011101110 ?
b1011101110 r
b110000110 C
b110000110 W
b110000110 ]
b1000011100 B
b1000011100 [
b1000011100 U
b11010010 R
b11010010 k
b10010 @
b10010 _
b100011101 S
b100011101 3
b100011101 h
b100011101 5
b100011101 g
1#
#380000
0#
#390000
b10000001011 V
b1011101110 8
b1011101110 l
b10000001011 ?
b10000001011 r
b1000011100 2
b1000011100 e
b10011 @
b10011 _
b1011101110 U
b100011101 R
b100011101 k
b1000011100 W
b1000011100 ]
b1011101110 B
b1011101110 [
b1000011100 C
b110000110 S
b110000110 3
b110000110 h
b110000110 5
b110000110 g
1#
#400000
0#
#410000
b1011101110 2
b1011101110 e
b10110010001 V
b10000001011 8
b10000001011 l
b10110010001 ?
b10110010001 r
b1011101110 C
b1011101110 W
b1011101110 ]
b10000001011 B
b10000001011 [
b10000001011 U
b110000110 R
b110000110 k
b10100 @
b10100 _
b1000011100 S
b1000011100 3
b1000011100 h
b1000011100 5
b1000011100 g
1#
#420000
0#
#430000
b11110101101 V
b10110010001 8
b10110010001 l
b11110101101 ?
b11110101101 r
b10000001011 2
b10000001011 e
b10101 @
b10101 _
b10110010001 U
b1000011100 R
b1000011100 k
b10000001011 W
b10000001011 ]
b10110010001 B
b10110010001 [
b10000001011 C
b1011101110 S
b1011101110 3
b1011101110 h
b1011101110 5
b1011101110 g
1#
#440000
0#
#450000
b10110010001 2
b10110010001 e
b101010011011 V
b11110101101 8
b11110101101 l
b101010011011 ?
b101010011011 r
b10110010001 C
b10110010001 W
b10110010001 ]
b11110101101 B
b11110101101 [
b11110101101 U
b1011101110 R
b1011101110 k
b10110 @
b10110 _
b10000001011 S
b10000001011 3
b10000001011 h
b10000001011 5
b10000001011 g
1#
