Data-Memory/data_memory.v
// 1kb data memory for MIPS microarch

module dataMemory (
    input               clk, rst, writeEnable,
    input      [31 : 0] address, dataWrite,
    output [31 : 0] dataOutput
);
    
    reg [31 : 0] data [1023 : 0];
    integer  i;
    always @(posedge clk, posedge rst) begin
        if(rst)begin
            data[32]<= 2;
            data[33]<= 0;
            data[34]<= 64;
            data[35]<= 4;
        end
        else if(writeEnable)   
                data[address] <= dataWrite;
    end

    assign dataOutput = data[address];
endmodule

ALU/alu.v

module ALU(
    input      [31 : 0] SrcA, SrcB,
    input      [2 : 0] ALUControl,
    output reg [31 : 0]ALUResult);

localparam 
add = 3'b010,
xorr= 3'b011,
sub = 3'b110,
andd= 3'b000,
orr = 3'b001, // ignore for now
slt = 3'b111; // ignore for now

always @(*) begin
    case (ALUControl)
        add :  ALUResult = SrcA + SrcB;
        sub :  ALUResult = SrcA - SrcB;
        andd:  ALUResult = SrcA & SrcB;
        xorr:  ALUResult = SrcA ^ SrcB;
        default: ALUResult = 0;
    endcase
end


endmodule

Register-File/register_file.v
module registerFile (
    input rst, clk, writeEnable,
    input [31 : 0] dataWrite,
    input [4 : 0] addressWrite, addressA, addressB,
    output reg [31 : 0] dataA, dataB
);
    integer  i;
    reg [31 : 0] registerFileData [31 : 0];


    always @(negedge clk, posedge rst) begin // don't forget the negedge instead of forwarding overhead.
        if(rst) begin
            for(i = 0; i < 32; i++)
                registerFileData[i] <= 0;
        end
        else if(writeEnable)
            registerFileData[addressWrite] = dataWrite;
    end



    always@(*)begin
        dataA = registerFileData[addressA];
        dataB = registerFileData[addressB];
    end
    wire [31 : 0] accumlator; assign accumlator = registerFileData[11];
    wire [31 : 0] xored; assign xored = registerFileData[13];
    wire [31 : 0] const2; assign const2 = registerFileData[10];
    wire [31 : 0] const64; assign const64 = registerFileData[12];
endmodule

Instruction-Memory/instruction_memory.v
// 1kb data memory for MIPS microarch

module instructionMemory (
    input           clk, rst,
    input  [31 : 0] address,
    output [31 : 0] instruction
);
    reg [31 : 0] data [1023 : 0];
    integer  i;
    always @(posedge clk, posedge rst) begin
        if(rst)begin
            for(i = 2;i < 1024;i++)
                data[i] <= 0;
            data[0] <= 32'b000000_10100_01010_01010_00000_100000; // add $t1, $t1, $some other register
        end
    end

    // data[0] <= 32'h8C0A0020;                              // lw $t1, 32($0), t1 = 5
    // data[1] <= 32'h8C0A0021;                              // lw $t1, 33($0), t1 = 6
    // data[1] <= 32'b000100_01010_01010_0000000000000011;   // beq $t1, $t1, add(5)

    assign instruction = data[address];

endmodule

data_path.v
`include "Instruction-Memory/instruction_memory.v"
`include "Data-Memory/data_memory.v"
`include "ALU/alu.v"
`include "Register-File/register_file.v"
`include "Program-Counter/program_counter.v"

module dataPath(
    input              rst, clk,
    input              regWrite, regDst, memWrite, mem2Reg, aluSrcB, pcSrc, enablePC,
    input      [2 : 0] aluControl,

    input      [1 : 0] fad, fbd,
    input              flushD, enableD, flushE,
    output     [4 : 0] rsDH, rtDH, rdEH, rdMH, 
    output     [5 : 0] opcode, funct,   
    output             eq, mem2RegEH, regWriteMH, regWriteEH, regWriteDH
);
    assign regWriteMH = regWriteM;
    assign regWriteEH = regWriteE;
    assign regWriteDH = regWrite;

    // fetch stage
    reg [31 : 0] PC; always@(posedge clk, posedge rst)if(rst)PC <= 0; else if(!enablePC) PC <= PC + (pcSrc ? immShiftedD : 1);
    wire [31 : 0] instr;
    instructionMemory IM(.clk(clk), .rst(rst), .instruction(instr), .address(PC));

    // decode stage
    reg [31 : 0] instrD;
    always @(posedge clk, posedge rst)if((flushD & clk) | rst)instrD <= 0; else if (!enableD)instrD <= instr;
    assign opcodeD = instrD[31 : 26];

    wire [4 : 0] rsD, rtD, rdD; assign rsD = instrD[25 : 21]; assign rtD = instrD[20 : 16]; assign rdD = instrD[15 : 11];
    wire [31 : 0] rsDataD, rtDataD;
    reg  [31 : 0] rsDataFD, rtDataFD;

    registerFile RF(.rst(rst), .clk(clk), .writeEnable(regWriteWB), .addressWrite(writeRegWB),
                .dataWrite(writeRegData), .addressA(rsD), .addressB(rtD), .dataA(rsDataD),
                .dataB(rtDataD));
    wire [31 : 0] immD; assign immD = {instrD[15]?16'hffff : 16'h0000 , instrD[15 : 0]};
    wire [31 : 0] immShiftedD = immD;
    assign eq = &(~(rsDataFD ^ rtDataFD));

    assign funct = instrD[5 : 0];
    assign opcode = instrD[31 : 26];
    // forward muxes
    always @(*) begin
        case (fad)
            0 : rsDataFD = rsDataD;     
            1 : rsDataFD = aluOutE; 
            2 : rsDataFD = memDataM;
            3 : rsDataFD = aluOutM;
            default: rsDataFD = 0;
        endcase
        case (fbd)
            0 : rtDataFD = rtDataD;     
            1 : rtDataFD = aluOutE; 
            2 : rtDataFD = memDataM;
            3 : rtDataFD = aluOutM;
            default: rtDataFD = 0;
        endcase
    end
    assign rsDH = rsD; 
    assign rtDH = rtD;

    // execute stage
    reg [31 : 0] rsDataE, rtDataE, immE;
    reg [5 : 0] rsE, rtE, rdE;
    reg regDstE, aluSrcBE, regWriteE, mem2RegE, memWriteE;
    reg [2 : 0] aluControlE;
    always @(posedge clk, posedge rst)begin
        if(rst | (clk & flushE))begin
            memWriteE   <= 0;
            regWriteE   <= 0;
        end else begin
            rsDataE     <= rsDataFD;
            rtDataE     <= rtDataFD;
            immE        <= immD;
            rsE         <= rsD;
            rtE         <= rtD;
            rdE         <= rdD;

            memWriteE   <= memWrite;
            mem2RegE    <= mem2Reg;
            regDstE     <= regDst;
            aluSrcBE    <= aluSrcB;
            aluControlE <= aluControl;
            regWriteE   <= regWrite;
        end
    end
    wire [31 : 0] operand2; assign operand2 = aluSrcBE?immE : rtDataE;
    wire [31 : 0] aluOutE;
    ALU a(.SrcA(rsDataE), .SrcB(operand2), .ALUControl(aluControlE), .ALUResult(aluOutE));
    wire [4 : 0] writeRegE; assign writeRegE = regDstE?rdE:rtE;

    assign rdEH = writeRegE;
    assign mem2RegEH = mem2RegE;

    // memory read stage
    reg [31 : 0] aluOutM, rtDataM;
    reg regWriteM, mem2RegM, memWriteM;
    reg [4 : 0] writeRegM;
    always @(posedge clk, posedge rst)begin
        if(rst)begin
            memWriteE   <= 0;
            regWriteE   <= 0;
        end else begin
            aluOutM <= aluOutE;
            rtDataM  <= rtDataE;
            writeRegM<= writeRegE;
            regWriteM<= regWriteE;
            mem2RegM  <= mem2RegE;
            memWriteM<= memWriteE;
        end
    end

    wire [31 : 0] memDataM;    
    dataMemory DM(.clk(clk), .rst(rst), .writeEnable(memWriteM), .address(aluOutM), .dataWrite(rtDataM),
                  .dataOutput(memDataM));

    assign rdMH = writeRegM;

    // writeback stage
    reg [31 : 0] memDataWB, aluOutWB;
    reg [4 : 0] writeRegWB;
    reg regWriteWB, mem2RegWB;
    always @(posedge clk, posedge rst)begin
        if(rst)begin
            memWriteE   <= 0;
            regWriteE   <= 0;
        end else begin
            regWriteWB <= regWriteM;
            memDataWB  <= memDataM;
            aluOutWB   <= aluOutM;
            writeRegWB <= writeRegM;
            mem2RegWB  <= mem2RegM;
        end
    end
    wire [31 : 0] writeRegData; assign writeRegData = mem2RegWB? memDataWB : aluOutWB;
endmodule
// Register file nomenclature
    // writeReg       => address of reg to write
    // writeRegData => data to be written
    // regWrite       => control signal to write

hazard_unit.v

module hazardUnit(input eq, regWriteEH, regWriteDH, mem2RegEH, regWriteMH,
          input [5 : 0] opcode, 
          input  [4 : 0] rsDH, rtDH, rdEH, rdMH, 
          output flushD, flushE, enableD, enablePC,
          output reg [1 : 0] fad, fbd
         );

    localparam beq   = 6'b000100;

    assign flushD = (opcode == beq) && eq;
    // stall if lw x, blabla; rtype f, x, x
    assign flushE = (mem2RegEH & regWriteEH) & ((rsDH == rdEH) | (rtDH == rdEH));
    assign enableD = (mem2RegEH & regWriteEH) & ((rsDH == rdEH) | (rtDH == rdEH)); 
    assign enablePC = (mem2RegEH & regWriteEH) & ((rsDH == rdEH) | (rtDH == rdEH)); 
    always @(*) begin
        if(regWriteEH && rsDH == rdEH && rdEH) // in execute
            fad = 1;
        else if(regWriteMH && rsDH == rdMH && rdMH) // in memory
            if(mem2RegEH) // I'm being smart and indicating if forwarding from the memory is needed without the regwriteM don't forget to remove it from the microarch design IDIOT!
                fad = 2;
            else
                fad = 3;
        else
            fad = 0;
    end
    always @(*) begin
        if(regWriteEH && rtDH == rdEH && rdEH)
            fbd = 1;
        else if(regWriteMH && rtDH == rdMH && rdMH)
            if(mem2RegEH) // I'm being smart and indicating if forwarding from the memory is needed without the regwriteM don't forget to remove it from the microarch design IDIOT!
                fbd = 2;
            else
                fbd = 3;
        else
            fbd = 0;
    end
endmodule

control_unit.v
module controlUnit(input [5 : 0] funct, opcode, 
                   input eq,
                   output reg regWrite, regDst, memWrite, mem2Reg, aluSrcB, pcSrc,
                   output reg [2 : 0] aluControl
                  );


// opcodes
localparam rType = 6'b000000,
            lw    = 6'b100011,
            sw    = 6'b101011,
            beq   = 6'b000100;

// funct fields
localparam add = 6'b100000;
localparam sub = 6'b100010;

always @(*)begin
    case (opcode)
        lw:     {pcSrc, regWrite, regDst, memWrite, mem2Reg, aluSrcB, aluControl} = {1'b0, 1'b1, 1'b0, 1'b0, 1'b1, 1'b1, 3'b010};
        sw:     {pcSrc, regWrite, regDst, memWrite, mem2Reg, aluSrcB, aluControl} = {1'b0, 1'b0, 1'b0, 1'b1, 1'b0, 1'b0, 3'b010};
        rType:  {pcSrc, regWrite, regDst, memWrite, mem2Reg, aluSrcB, aluControl} = {1'b0, 1'b1, 1'b1, 1'b0, 1'b0, 1'b0, (funct == add) ? 3'b010 : (funct == sub?3'b110 : 3'b011)};
        beq:    {pcSrc, regWrite, regDst, memWrite, mem2Reg, aluSrcB, aluControl} = {eq, 1'b0, 1'b0, 1'b0, 1'b0, 1'b0, 3'b010};
        default:{pcSrc, regWrite, regDst, memWrite, mem2Reg, aluSrcB, aluControl} = {1'b0, 1'b0, 1'b0, 1'b0, 1'b0, 1'b0, 3'b010};
    endcase
end

endmodule


// TODO : update the static branch predictor to a 2 bit saturation dynamic one
// now it makes sense why in the ISA we choose distance is from the next instruction preceding the branch instruction, because
// the static branch predictor is used and the next instruction is already fetched and PC is pointing at it while beq is at decode.

mips.v
`include "data_path.v"
`include "control_unit.v"
`include "hazard_unit.v"
module mips(input clk, rst);

    wire [5 : 0] funct, opcode;
    wire         eq, regWrite, regWriteEH, regWriteMH, regWriteDH,
                 regDst, memWrite, mem2RegEH, aluSrcB, pcSrc, flush,
                 mem2RegEE, flushE, enableD, flushD, enablePC;
    wire [2 : 0] aluControl;
    wire [1 : 0] fad, fbd;
    wire [4 : 0] rsDH, rtDH, rdEH, rdMH;

    controlUnit cu(.eq(eq), .regWrite(regWrite), .regDst(regDst),
                   .memWrite(memWrite), .mem2Reg(mem2Reg), .aluSrcB(aluSrcB), 
                   .pcSrc(pcSrc), .aluControl(aluControl), .opcode(opcode),
                   .funct(funct));

    hazardUnit hu(.eq(eq), .regWriteEH(regWriteEH), .regWriteDH(regWriteDH), 
                  .mem2RegEH(mem2RegEH), .regWriteMH(regWriteMH), .opcode(opcode), 
                  .rsDH(rsDH), .rtDH(rtDH), .rdEH(rdEH), .rdMH(rdMH), .flushD(flushD), 
                  .flushE(flushE), .fad(fad), .fbd(fbd), .enableD(enableD), .enablePC(enablePC));

    dataPath    dp(.rst(rst), .clk(clk), .regWrite(regWrite), .regDst(regDst),
                   .memWrite(memWrite), .mem2Reg(mem2Reg), .aluSrcB(aluSrcB), 
                   .pcSrc(pcSrc), .aluControl(aluControl), .fad(fad), .fbd(fbd),
                   .flushE(flushE), .rsDH(rsDH), .rtDH(rtDH), .rdEH(rdEH), .rdMH(rdMH),
                   .opcode(opcode), .funct(funct), .eq(eq), .mem2RegEH(mem2RegEH), 
                   .regWriteMH(regWriteMH), .regWriteEH(regWriteEH),.regWriteDH(regWriteDH),
                   .flushD(flushD), .enableD(enableD), .enablePC(enablePC));

    
endmodule

mips_testbench.v
`include "mips.v"
`timescale 1ns/1ps

module tb;


    reg clk, rst;
    always #10 clk ^= 1;

    mips m(.clk(clk), .rst(rst));

    initial begin
        $dumpfile("mips_testbench.vcd");
        $dumpvars(0, tb);

        clk = 0;
        rst = 1;
        #5;
        rst = 0;

        #350;
        $finish;
    end


endmodule

mips_testbench.vcd
$date
	Tue Jul 16 13:23:49 2024
$end
$version
	Icarus Verilog
$end
$timescale
	1ps
$end
$scope module tb $end
$var reg 1 ! clk $end
$var reg 1 " rst $end
$scope module m $end
$var wire 1 ! clk $end
$var wire 1 " rst $end
$var wire 5 # rtDH [4:0] $end
$var wire 5 $ rsDH [4:0] $end
$var wire 1 % regWriteMH $end
$var wire 1 & regWriteEH $end
$var wire 1 ' regWriteDH $end
$var wire 1 ( regWrite $end
$var wire 1 ) regDst $end
$var wire 5 * rdMH [4:0] $end
$var wire 5 + rdEH [4:0] $end
$var wire 1 , pcSrc $end
$var wire 6 - opcode [5:0] $end
$var wire 1 . memWrite $end
$var wire 1 / mem2RegEH $end
$var wire 1 0 mem2Reg $end
$var wire 6 1 funct [5:0] $end
$var wire 1 2 flushE $end
$var wire 1 3 flushD $end
$var wire 2 4 fbd [1:0] $end
$var wire 2 5 fad [1:0] $end
$var wire 1 6 eq $end
$var wire 1 7 enablePC $end
$var wire 1 8 enableD $end
$var wire 1 9 aluSrcB $end
$var wire 3 : aluControl [2:0] $end
$scope module cu $end
$var wire 6 ; opcode [5:0] $end
$var wire 6 < funct [5:0] $end
$var wire 1 6 eq $end
$var parameter 6 = add $end
$var parameter 6 > beq $end
$var parameter 6 ? lw $end
$var parameter 6 @ rType $end
$var parameter 6 A sub $end
$var parameter 6 B sw $end
$var reg 3 C aluControl [2:0] $end
$var reg 1 9 aluSrcB $end
$var reg 1 0 mem2Reg $end
$var reg 1 . memWrite $end
$var reg 1 , pcSrc $end
$var reg 1 ) regDst $end
$var reg 1 ( regWrite $end
$upscope $end
$scope module dp $end
$var wire 3 D aluControl [2:0] $end
$var wire 1 9 aluSrcB $end
$var wire 1 ! clk $end
$var wire 32 E immShiftedD [31:0] $end
$var wire 1 0 mem2Reg $end
$var wire 1 / mem2RegEH $end
$var wire 1 . memWrite $end
$var wire 1 , pcSrc $end
$var wire 5 F rdEH [4:0] $end
$var wire 5 G rdMH [4:0] $end
$var wire 1 ) regDst $end
$var wire 1 ( regWrite $end
$var wire 1 ' regWriteDH $end
$var wire 1 & regWriteEH $end
$var wire 1 % regWriteMH $end
$var wire 5 H rsDH [4:0] $end
$var wire 1 " rst $end
$var wire 5 I rtDH [4:0] $end
$var wire 5 J writeRegE [4:0] $end
$var wire 32 K writeRegData [31:0] $end
$var wire 32 L rtDataD [31:0] $end
$var wire 5 M rtD [4:0] $end
$var wire 32 N rsDataD [31:0] $end
$var wire 5 O rsD [4:0] $end
$var wire 5 P rdD [4:0] $end
$var wire 32 Q operand2 [31:0] $end
$var wire 1 R opcodeD $end
$var wire 6 S opcode [5:0] $end
$var wire 32 T memDataM [31:0] $end
$var wire 32 U instr [31:0] $end
$var wire 32 V immD [31:0] $end
$var wire 6 W funct [5:0] $end
$var wire 1 2 flushE $end
$var wire 1 3 flushD $end
$var wire 2 X fbd [1:0] $end
$var wire 2 Y fad [1:0] $end
$var wire 1 6 eq $end
$var wire 1 7 enablePC $end
$var wire 1 8 enableD $end
$var wire 32 Z aluOutE [31:0] $end
$var reg 32 [ PC [31:0] $end
$var reg 3 \ aluControlE [2:0] $end
$var reg 32 ] aluOutM [31:0] $end
$var reg 32 ^ aluOutWB [31:0] $end
$var reg 1 _ aluSrcBE $end
$var reg 32 ` immE [31:0] $end
$var reg 32 a instrD [31:0] $end
$var reg 1 / mem2RegE $end
$var reg 1 b mem2RegM $end
$var reg 1 c mem2RegWB $end
$var reg 32 d memDataWB [31:0] $end
$var reg 1 e memWriteE $end
$var reg 1 f memWriteM $end
$var reg 6 g rdE [5:0] $end
$var reg 1 h regDstE $end
$var reg 1 & regWriteE $end
$var reg 1 i regWriteM $end
$var reg 1 j regWriteWB $end
$var reg 32 k rsDataE [31:0] $end
$var reg 32 l rsDataFD [31:0] $end
$var reg 6 m rsE [5:0] $end
$var reg 32 n rtDataE [31:0] $end
$var reg 32 o rtDataFD [31:0] $end
$var reg 32 p rtDataM [31:0] $end
$var reg 6 q rtE [5:0] $end
$var reg 5 r writeRegM [4:0] $end
$var reg 5 s writeRegWB [4:0] $end
$scope module DM $end
$var wire 32 t address [31:0] $end
$var wire 1 ! clk $end
$var wire 32 u dataOutput [31:0] $end
$var wire 32 v dataWrite [31:0] $end
$var wire 1 " rst $end
$var wire 1 f writeEnable $end
$upscope $end
$scope module IM $end
$var wire 32 w address [31:0] $end
$var wire 1 ! clk $end
$var wire 32 x instruction [31:0] $end
$var wire 1 " rst $end
$var integer 32 y i [31:0] $end
$upscope $end
$scope module RF $end
$var wire 32 z accumlator [31:0] $end
$var wire 5 { addressA [4:0] $end
$var wire 5 | addressB [4:0] $end
$var wire 5 } addressWrite [4:0] $end
$var wire 1 ! clk $end
$var wire 32 ~ const2 [31:0] $end
$var wire 32 !" const64 [31:0] $end
$var wire 32 "" dataWrite [31:0] $end
$var wire 1 " rst $end
$var wire 1 j writeEnable $end
$var wire 32 #" xored [31:0] $end
$var reg 32 $" dataA [31:0] $end
$var reg 32 %" dataB [31:0] $end
$var integer 32 &" i [31:0] $end
$upscope $end
$scope module a $end
$var wire 3 '" ALUControl [2:0] $end
$var wire 32 (" SrcA [31:0] $end
$var wire 32 )" SrcB [31:0] $end
$var parameter 3 *" add $end
$var parameter 3 +" andd $end
$var parameter 3 ," orr $end
$var parameter 3 -" slt $end
$var parameter 3 ." sub $end
$var parameter 3 /" xorr $end
$var reg 32 0" ALUResult [31:0] $end
$upscope $end
$upscope $end
$scope module hu $end
$var wire 1 8 enableD $end
$var wire 1 7 enablePC $end
$var wire 1 6 eq $end
$var wire 1 3 flushD $end
$var wire 1 2 flushE $end
$var wire 1 / mem2RegEH $end
$var wire 6 1" opcode [5:0] $end
$var wire 5 2" rdEH [4:0] $end
$var wire 5 3" rdMH [4:0] $end
$var wire 1 ' regWriteDH $end
$var wire 1 & regWriteEH $end
$var wire 1 % regWriteMH $end
$var wire 5 4" rsDH [4:0] $end
$var wire 5 5" rtDH [4:0] $end
$var parameter 6 6" beq $end
$var reg 2 7" fad [1:0] $end
$var reg 2 8" fbd [1:0] $end
$upscope $end
$upscope $end
$upscope $end
$enddefinitions $end
$comment Show the parameter values. $end
$dumpall
b100 6"
b11 /"
b110 ."
b111 -"
b1 ,"
b0 +"
b10 *"
b101011 B
b100010 A
b0 @
b100011 ?
b100 >
b100000 =
$end
#0
$dumpvars
b0 8"
b0 7"
b0 5"
b0 4"
bx 3"
bx 2"
b0 1"
bx 0"
bx )"
bx ("
bx '"
b100000 &"
b0 %"
b0 $"
b0 #"
bx ""
b0 !"
b0 ~
bx }
b0 |
b0 {
b0 z
b10000000000 y
b10001100000010100000000000100000 x
b0 w
bx v
bx u
bx t
bx s
bx r
bx q
bx p
b0 o
bx n
bx m
b0 l
bx k
xj
xi
xh
bx g
xf
0e
bx d
xc
xb
b0 a
bx `
x_
bx ^
bx ]
bx \
b0 [
bx Z
b0 Y
b0 X
b0 W
b0 V
b10001100000010100000000000100000 U
bx T
b0 S
0R
bx Q
b0 P
b0 O
b0 N
b0 M
b0 L
bx K
bx J
b0 I
b0 H
bx G
bx F
b0 E
b11 D
b11 C
b0 <
b0 ;
b11 :
09
08
07
16
b0 5
b0 4
03
02
b0 1
00
x/
0.
b0 -
0,
bx +
bx *
1)
1(
1'
0&
x%
b0 $
b0 #
1"
0!
$end
#5000
0"
#10000
b0 +
b0 F
b0 2"
b0 J
b0 Z
b0 0"
1R
0)
10
19
b10 :
b10 C
b10 D
b0 Q
b0 )"
b1010 #
b1010 I
b1010 5"
b1010 M
b1010 |
b100000 E
b100000 V
b100000 1
b100000 <
b100000 W
b100011 -
b100011 ;
b100011 S
b100011 1"
0f
0%
0i
1&
b11 \
b11 '"
0_
1h
0/
b0 g
b0 q
b0 m
b0 `
b0 n
b0 k
b0 ("
b10001100000010100000000000100000 a
b10001100000010110000000000100001 U
b10001100000010110000000000100001 x
b1 [
b1 w
1!
#20000
0!
#30000
b1010 +
b1010 F
b1010 2"
b1010 J
02
08
07
b1011 #
b1011 I
b1011 5"
b1011 M
b1011 |
b100001 E
b100001 V
b100001 1
b100001 <
b100001 W
b100000 Z
b100000 0"
b100000 Q
b100000 )"
b10001100000011000000000000100010 U
b10001100000011000000000000100010 x
b10 [
b10 w
b10001100000010110000000000100001 a
b10 \
b10 '"
1_
0h
1/
b1010 q
b100000 `
0b
1%
1i
b0 *
b0 G
b0 3"
b0 r
b0 p
b0 v
b0 ]
b0 t
0j
1!
#40000
0!
#50000
b1011 +
b1011 F
b1011 2"
b1011 J
b100001 Z
b100001 0"
b0 K
b0 ""
b100001 Q
b100001 )"
b1100 #
b1100 I
b1100 5"
b1100 M
b1100 |
b100010 E
b100010 V
b100010 1
b100010 <
b100010 W
0c
b0 s
b0 }
b0 ^
1j
1b
b1010 *
b1010 G
b1010 3"
b1010 r
b10 T
b10 u
b100000 ]
b100000 t
b1011 q
b100001 `
b10001100000011000000000000100010 a
b10001100000011010000000000100011 U
b10001100000011010000000000100011 x
b11 [
b11 w
1!
#60000
0!
#70000
b1100 +
b1100 F
b1100 2"
b1100 J
b100010 Z
b100010 0"
b1101 #
b1101 I
b1101 5"
b1101 M
b1101 |
b100011 E
b100011 V
b100011 1
b100011 <
b100011 W
b100010 Q
b100010 )"
b10 K
b10 ""
b10000000011010000000000000011 U
b10000000011010000000000000011 x
b100 [
b100 w
b10001100000011010000000000100011 a
b1100 q
b100010 `
b1011 *
b1011 G
b1011 3"
b1011 r
b0 T
b0 u
b100001 ]
b100001 t
1c
b1010 s
b1010 }
b100000 ^
b10 d
1!
#80000
b10 ~
0!
#90000
06
b100011 o
12
18
17
b1 4
b1 X
b1 8"
b1101 +
b1101 F
b1101 2"
b1101 J
b100011 Z
b100011 0"
0R
03
0,
0'
0(
00
09
b0 K
b0 ""
b100011 Q
b100011 )"
b11 E
b11 V
b11 1
b11 <
b11 W
b100 -
b100 ;
b100 S
b100 1"
b1011 s
b1011 }
b100001 ^
b0 d
b1100 *
b1100 G
b1100 3"
b1100 r
b1000000 T
b1000000 u
b100010 ]
b100010 t
b1101 q
b100011 `
b10000000011010000000000000011 a
b1010010110101100000100000 U
b1010010110101100000100000 x
b101 [
b101 w
1!
#100000
0!
#110000
02
08
07
b100 o
b10 4
b10 X
b10 8"
b1000000 K
b1000000 ""
0&
b1101 *
b1101 G
b1101 3"
b1101 r
b100 T
b100 u
b100011 ]
b100011 t
b1100 s
b1100 }
b100010 ^
b1000000 d
1!
#120000
b1000000 !"
0!
#130000
b0 o
b10 l
b100 Z
b100 0"
b10 N
b10 $"
1'
1(
1)
b100 K
b100 ""
b0 4
b0 X
b0 8"
b100 Q
b100 )"
b1010 $
b1010 H
b1010 4"
b1010 O
b1010 {
b1011 #
b1011 I
b1011 5"
b1011 M
b1011 |
b1011 P
b101100000100000 E
b101100000100000 V
b100000 1
b100000 <
b100000 W
b0 -
b0 ;
b0 S
b0 1"
b1101 s
b1101 }
b100011 ^
b100 d
0%
0i
0_
0/
b11 `
b100 n
b1010010110101100000100000 a
b1100010110110100000100110 U
b1100010110110100000100110 x
b110 [
b110 w
1!
#140000
b100 #"
0!
#150000
b10 o
b1 4
b1 X
b1 8"
b1000000 l
b1000000 N
b1000000 $"
b11 :
b11 C
b11 D
b1011 +
b1011 F
b1011 2"
b1011 J
b1100 $
b1100 H
b1100 4"
b1100 O
b1100 {
b1101 P
b110100000100110 E
b110100000100110 V
b100110 1
b100110 <
b100110 W
b0 Q
b0 )"
b10 Z
b10 0"
b10000000000001111111111111100 U
b10000000000001111111111111100 x
b111 [
b111 w
b1100010110110100000100110 a
1&
1h
b1011 g
b1011 q
b1010 m
b101100000100000 `
b0 n
b10 k
b10 ("
0b
b100 p
b100 v
bx T
bx u
b100 ]
b100 t
0j
1!
#160000
0!
#170000
13
1,
16
b0 l
b1101 +
b1101 F
b1101 2"
b1101 J
b0 N
b0 $"
0'
0(
0)
b10 :
b10 C
b10 D
b0 4
b0 X
b0 8"
b0 o
b10 Q
b10 )"
b1000010 Z
b1000010 0"
b0 $
b0 H
b0 4"
b0 O
b0 {
b0 #
b0 I
b0 5"
b0 M
b0 |
b11111 P
b11111111111111111111111111111100 E
b11111111111111111111111111111100 V
b111100 1
b111100 <
b111100 W
b100 -
b100 ;
b100 S
b100 1"
0c
b100 ^
bx d
1%
1i
b1011 *
b1011 G
b1011 3"
b1011 r
b0 p
b0 v
b10 ]
b10 t
b11 \
b11 '"
b1101 g
b1100 m
b110100000100110 `
b10 n
b1000000 k
b1000000 ("
b10000000000001111111111111100 a
b0 U
b0 x
b1000 [
b1000 w
1!
#180000
0!
#190000
03
0,
1'
1(
1)
b11 :
b11 C
b11 D
b0 +
b0 F
b0 2"
b0 J
b0 P
b0 E
b0 V
b0 1
b0 <
b0 W
b0 -
b0 ;
b0 S
b0 1"
b0 Q
b0 )"
b0 Z
b0 0"
b10 K
b10 ""
b10000000011010000000000000011 U
b10000000011010000000000000011 x
b100 [
b100 w
b0 a
0&
b10 \
b10 '"
0h
b11111 g
b0 q
b0 m
b11111111111111111111111111111100 `
b0 n
b0 k
b0 ("
b1101 *
b1101 G
b1101 3"
b1101 r
b10 p
b10 v
b1000010 ]
b1000010 t
b1011 s
b1011 }
b10 ^
1j
1!
#200000
b10 z
0!
#210000
06
b100 o
b100 L
b100 %"
03
0,
0'
0(
0)
b10 :
b10 C
b10 D
b1000010 K
b1000010 ""
b1101 #
b1101 I
b1101 5"
b1101 M
b1101 |
b11 E
b11 V
b11 1
b11 <
b11 W
b100 -
b100 ;
b100 S
b100 1"
b1101 s
b1101 }
b1000010 ^
0%
0i
b0 *
b0 G
b0 3"
b0 r
b0 p
b0 v
b0 ]
b0 t
1&
b11 \
b11 '"
1h
b0 g
b0 `
b10000000011010000000000000011 a
b1010010110101100000100000 U
b1010010110101100000100000 x
b101 [
b101 w
1!
#220000
b1000010 o
b1000010 L
b1000010 %"
b1000010 #"
0!
#230000
16
b10 o
b10 l
b10 L
b10 %"
b10 N
b10 $"
1'
1(
1)
b1101 +
b1101 F
b1101 2"
b1101 J
b1010 $
b1010 H
b1010 4"
b1010 O
b1010 {
b1011 #
b1011 I
b1011 5"
b1011 M
b1011 |
b1011 P
b101100000100000 E
b101100000100000 V
b100000 1
b100000 <
b100000 W
b0 -
b0 ;
b0 S
b0 1"
b1000010 Z
b1000010 0"
b1000010 Q
b1000010 )"
b0 K
b0 ""
b1100010110110100000100110 U
b1100010110110100000100110 x
b110 [
b110 w
b1010010110101100000100000 a
0&
b10 \
b10 '"
0h
b1101 q
b11 `
b1000010 n
1%
1i
b0 s
b0 }
b0 ^
0j
1!
#240000
0!
#250000
06
b100 o
b1 4
b1 X
b1 8"
b1000000 l
b1011 +
b1011 F
b1011 2"
b1011 J
b1000000 N
b1000000 $"
b11 :
b11 C
b11 D
b10 Q
b10 )"
b100 Z
b100 0"
b1100 $
b1100 H
b1100 4"
b1100 O
b1100 {
b1101 P
b110100000100110 E
b110100000100110 V
b100110 1
b100110 <
b100110 W
1j
0%
0i
b1101 *
b1101 G
b1101 3"
b1101 r
b1000010 p
b1000010 v
b1000010 ]
b1000010 t
1&
1h
b1011 g
b1011 q
b1010 m
b101100000100000 `
b10 n
b10 k
b10 ("
b1100010110110100000100110 a
b10000000000001111111111111100 U
b10000000000001111111111111100 x
b111 [
b111 w
1!
#260000
0!
#270000
13
1,
16
b0 l
b0 L
b0 %"
b0 N
b0 $"
b0 4
b0 X
b0 8"
0'
0(
0)
b10 :
b10 C
b10 D
b1101 +
b1101 F
b1101 2"
b1101 J
b0 o
b0 $
b0 H
b0 4"
b0 O
b0 {
b0 #
b0 I
b0 5"
b0 M
b0 |
b11111 P
b11111111111111111111111111111100 E
b11111111111111111111111111111100 V
b111100 1
b111100 <
b111100 W
b100 -
b100 ;
b100 S
b100 1"
b100 Q
b100 )"
b1000100 Z
b1000100 0"
b1000010 K
b1000010 ""
b0 U
b0 x
b1000 [
b1000 w
b10000000000001111111111111100 a
b11 \
b11 '"
b1101 g
b1100 m
b110100000100110 `
b100 n
b1000000 k
b1000000 ("
1%
1i
b1011 *
b1011 G
b1011 3"
b1011 r
b10 p
b10 v
b100 ]
b100 t
b1101 s
b1101 }
b1000010 ^
0j
1!
#280000
0!
#290000
b0 +
b0 F
b0 2"
b0 J
03
0,
1'
1(
1)
b11 :
b11 C
b11 D
b100 K
b100 ""
b0 Q
b0 )"
b0 Z
b0 0"
b0 P
b0 E
b0 V
b0 1
b0 <
b0 W
b0 -
b0 ;
b0 S
b0 1"
b1011 s
b1011 }
b100 ^
1j
b1101 *
b1101 G
b1101 3"
b1101 r
b100 p
b100 v
b1000100 ]
b1000100 t
0&
b10 \
b10 '"
0h
b11111 g
b0 q
b0 m
b11111111111111111111111111111100 `
b0 n
b0 k
b0 ("
b0 a
b10000000011010000000000000011 U
b10000000011010000000000000011 x
b100 [
b100 w
1!
#300000
b100 z
0!
