Data-Memory/data_memory.v
// 1kb data memory for MIPS microarch

module dataMemory (
    input               clk, rst, writeEnable,
    input      [31 : 0] address, dataWrite,
    output [31 : 0] dataOutput
);
    
    reg [31 : 0] data [1023 : 0];
    integer  i;
    always @(posedge clk, posedge rst) begin
        if(rst)begin
            data[32]<= 2;
            data[33]<= 0;
            data[34]<= 64;
            data[35]<= 4;
        end
        else if(writeEnable)   
                data[address] <= dataWrite;
    end

    assign dataOutput = data[address];
endmodule

ALU/alu.v

module ALU(
    input      [31 : 0] SrcA, SrcB,
    input      [2 : 0] ALUControl,
    output reg [31 : 0]ALUResult);

localparam 
add = 3'b010,
xorr= 3'b011,
sub = 3'b110,
andd= 3'b000,
orr = 3'b001, // ignore for now
slt = 3'b111; // ignore for now

always @(*) begin
    case (ALUControl)
        add :  ALUResult = SrcA + SrcB;
        sub :  ALUResult = SrcA - SrcB;
        andd:  ALUResult = SrcA & SrcB;
        xorr:  ALUResult = SrcA ^ SrcB;
        default: ALUResult = 0;
    endcase
end


endmodule

Register-File/register_file.v
module registerFile (
    input rst, clk, writeEnable,
    input [31 : 0] dataWrite,
    input [4 : 0] addressWrite, addressA, addressB,
    output reg [31 : 0] dataA, dataB
);
    integer  i;
    reg [31 : 0] registerFileData [31 : 0];


    always @(negedge clk, posedge rst) begin // don't forget the negedge instead of forwarding overhead.
        if(rst) begin
            for(i = 0; i < 32; i++)
                registerFileData[i] <= 0;
        end
        else if(writeEnable)
            registerFileData[addressWrite] = dataWrite;
    end



    always@(*)begin
        dataA = registerFileData[addressA];
        dataB = registerFileData[addressB];
    end
    wire [31 : 0] accumlator; assign accumlator = registerFileData[11];
    wire [31 : 0] xored; assign xored = registerFileData[13];
    wire [31 : 0] const2; assign const2 = registerFileData[10];
    wire [31 : 0] const64; assign const64 = registerFileData[12];
endmodule

Instruction-Memory/instruction_memory.v
// 1kb data memory for MIPS microarch

module instructionMemory (
    input           clk, rst,
    input  [31 : 0] address,
    output [31 : 0] instruction
);
    reg [31 : 0] data [1023 : 0];
    integer  i;
    always @(posedge clk, posedge rst) begin
        if(rst)begin
            data[0] = 32'b100011_00000_01010_0000000000100000;
            data[1] = 32'b100011_00000_01011_0000000000100001;
            data[2] = 32'b100011_00000_01100_0000000000100010;
            data[3] = 32'b100011_00000_01101_0000000000100011;
            data[4] = 32'b000100_00000_01101_0000000000000011;
            data[5] = 32'b000000_01010_01011_01011_00000_100000;
            data[6] = 32'b000000_01100_01011_01101_00000_100110;
            data[7] = 32'b000100_00000_00000_1111111111111100;
            for(i = 8;i < 1024;i++)
                data[i] = 0;
        end
    end
    assign instruction = data[address];


endmodule





// data[0] <= 32'b000000_10100_01010_01010_00000_100000; // add $t1, $t1, $some other register
// data[1] <= 32'b000100_01010_01010_0000000000000011;   // beq $t1, $t1, add(5)
// data[5] <= 32'b000000_10100_01010_01010_00000_100000; // add $t1, $t1, $some other register
// data[0] <= 32'h8C0A0020;                              // lw $t1, 32($0), t1 = 5
// data[1] <= 32'h8C0A0021;                              // lw $t1, 33($0), t1 = 6
// data[1] <= 32'b000100_01010_01010_0000000000000011;   // beq $t1, $t1, add(5)

data_path.v
`include "Instruction-Memory/instruction_memory.v"
`include "Data-Memory/data_memory.v"
`include "ALU/alu.v"
`include "Register-File/register_file.v"
`include "Program-Counter/program_counter.v"

module dataPath(
    input              rst, clk,
    input              regWrite, regDst, memWrite, mem2Reg, aluSrcB, pcSrc,
    input      [2 : 0] aluControl,

    input      [1 : 0] fad, fbd,
    input              flushD, enableD, enableE,
    output     [4 : 0] rsDH, rtDH, rdEH, rdMH, 
    output     [5 : 0] opcode, funct,   
    output             eq, mem2RegEH, regWriteMH, regWriteEH, regWriteDH
);
    assign regWriteMH = regWriteE;
    assign regWriteEH = regWriteM;
    assign regWriteDH = regWrite;

    // fetch stage
    reg [31 : 0] PC; always@(posedge clk, posedge rst)if(rst)PC <= 0; else PC <= PC + (pcSrc ? immShiftedD : 1);
    wire [31 : 0] instr;
    instructionMemory IM(.clk(clk), .rst(rst), .instruction(instr), .address(PC));

    // decode stage
    reg [31 : 0] instrD;
    always @(posedge clk, posedge rst)if((flushD & clk) | rst)instrD <= 0; else if (!enableD)instrD <= instr;
    assign opcodeD = instrD[31 : 26];

    wire [4 : 0] rsD, rtD, rdD; assign rsD = instrD[25 : 21]; assign rtD = instrD[20 : 16]; assign rdD = instrD[15 : 11];
    wire [31 : 0] rsDataD, rtDataD;
    reg  [31 : 0] rsDataFD, rtDataFD;

    registerFile RF(.rst(rst), .clk(clk), .writeEnable(regWriteWB), .addressWrite(writeRegWB),
                .dataWrite(writeRegData), .addressA(rsD), .addressB(rtD), .dataA(rsDataD),
                .dataB(rtDataD));
    wire [31 : 0] immD; assign immD = {instrD[15]?16'hffff : 16'h0000 , instrD[15 : 0]};
    wire [31 : 0] immShiftedD = immD;
    assign eq = &(~(rsDataFD ^ rtDataFD));

    assign funct = instrD[5 : 0];
    assign opcode = instrD[31 : 26];
    // forward muxes
    always @(*) begin
        case (fad)
            0 : rsDataFD = rsDataD;     
            1 : rsDataFD = aluOutE; 
            2 : rsDataFD = memDataM;
            3 : rsDataFD = aluOutM;
            default: rsDataFD = 0;
        endcase
        case (fbd)
            0 : rtDataFD = rtDataD;     
            1 : rtDataFD = aluOutE; 
            2 : rtDataFD = memDataM;
            3 : rtDataFD = aluOutM;
            default: rtDataFD = 0;
        endcase
    end
    assign rsDH = rsD; 
    assign rtDH = rtD;

    // execute stage
    reg [31 : 0] rsDataE, rtDataE, immE;
    reg [5 : 0] rsE, rtE, rdE;
    reg regDstE, aluSrcBE, regWriteE, mem2RegE, memWriteE;
    reg [2 : 0] aluControlE;
    always @(posedge clk, posedge rst)begin
        if(rst)begin
            memWriteE   <= 0;
            regWriteE   <= 0;
        end else if(!enableE) begin
            rsDataE     <= rsDataFD;
            rtDataE     <= rtDataFD;
            immE        <= immD;
            rsE         <= rsD;
            rtE         <= rtD;
            rdE         <= rdD;

            memWriteE   <= memWrite;
            mem2RegE    <= mem2Reg;
            regDstE     <= regDst;
            aluSrcBE    <= aluSrcB;
            aluControlE <= aluControl;
            regWriteE   <= regWrite;
        end
    end
    wire [31 : 0] operand2; assign operand2 = aluSrcBE?immE : rtDataE;
    wire [31 : 0] aluOutE;
    ALU a(.SrcA(rsDataE), .SrcB(operand2), .ALUControl(aluControlE), .ALUResult(aluOutE));
    wire [4 : 0] writeRegE; assign writeRegE = regDstE?rdE:rtE;

    assign rdEH = writeRegE;
    assign mem2RegEH = mem2RegE;

    // memory read stage
    reg [31 : 0] aluOutM, rtDataM;
    reg regWriteM, mem2RegM, memWriteM;
    reg [4 : 0] writeRegM;
    always @(posedge clk, posedge rst)begin
        if(rst)begin
            memWriteE   <= 0;
            regWriteE   <= 0;
        end else begin
            aluOutM <= aluOutE;
            rtDataM  <= rtDataE;
            writeRegM<= writeRegE;
            regWriteM<= regWriteE;
            mem2RegM  <= mem2RegE;
            memWriteM<= memWriteE;
        end
    end

    wire [31 : 0] memDataM;    
    dataMemory DM(.clk(clk), .rst(rst), .writeEnable(memWriteM), .address(aluOutM), .dataWrite(rtDataM),
                  .dataOutput(memDataM));

    assign rdMH = writeRegM;

    // writeback stage
    reg [31 : 0] memDataWB, aluOutWB;
    reg [4 : 0] writeRegWB;
    reg regWriteWB, mem2RegWB;
    always @(posedge clk, posedge rst)begin
        if(rst)begin
            memWriteE   <= 0;
            regWriteE   <= 0;
        end else begin
            regWriteWB <= regWriteM;
            memDataWB  <= memDataM;
            aluOutWB   <= aluOutM;
            writeRegWB <= writeRegM;
            mem2RegWB  <= mem2RegM;
        end
    end
    wire [31 : 0] writeRegData; assign writeRegData = mem2RegWB? memDataWB : aluOutWB;
endmodule
// Register file nomenclature
    // writeReg       => address of reg to write
    // writeRegData => data to be written
    // regWrite       => control signal to write

hazard_unit.v

module hazardUnit(input eq, regWriteEH, regWriteDH, mem2RegEH, regWriteMH,
          input [5 : 0] opcode, 
          input  [4 : 0] rsDH, rtDH, rdEH, rdMH, 
          output flushD, enableE, enableD,
          output reg [1 : 0] fad, fbd
         );

    localparam beq   = 6'b000100;

    assign flushD = (opcode == beq) && eq;
    // stall if lw x, blabla; rtype f, x, x
    assign enableE = (mem2RegEH & regWriteEH) & ((rsDH == rdEH) | (rtDH == rdEH));
    assign enableD = (mem2RegEH & regWriteEH) & ((rsDH == rdEH) | (rtDH == rdEH)); 
    always @(*) begin
        if(regWriteEH && rsDH == rdEH)
            fad = 1;
        else if(regWriteEH && rsDH == rdMH)
            if(mem2RegEH) // I'm being smart and indicating if forwarding from the memory is needed without the regwriteM don't forget to remove it from the microarch design IDIOT!
                fad = 2;
            else
                fad = 3;
        else
            fad = 0;
    end
    always @(*) begin
        if(regWriteEH && rtDH == rdEH)
            fbd = 1;
        else if(regWriteEH && rtDH == rdMH)
            if(mem2RegEH) // I'm being smart and indicating if forwarding from the memory is needed without the regwriteM don't forget to remove it from the microarch design IDIOT!
                fbd = 2;
            else
                fbd = 3;
        else
            fbd = 0;
    end
endmodule

control_unit.v
module controlUnit(input [5 : 0] funct, opcode, 
                   input eq,
                   output reg regWrite, regDst, memWrite, mem2Reg, aluSrcB, pcSrc,
                   output reg [2 : 0] aluControl
                  );


// opcodes
localparam rType = 6'b000000,
            lw    = 6'b100011,
            sw    = 6'b101011,
            beq   = 6'b000100;

// funct fields
localparam add = 6'b100000;
localparam sub = 6'b100010;

always @(*)begin
    case (opcode)
        lw:     {pcSrc, regWrite, regDst, memWrite, mem2Reg, aluSrcB, aluControl} = {1'b0, 1'b1, 1'b0, 1'b0, 1'b1, 1'b1, 3'b010};
        sw:     {pcSrc, regWrite, regDst, memWrite, mem2Reg, aluSrcB, aluControl} = {1'b0, 1'b0, 1'b0, 1'b1, 1'b0, 1'b0, 3'b010};
        rType:  {pcSrc, regWrite, regDst, memWrite, mem2Reg, aluSrcB, aluControl} = {1'b0, 1'b1, 1'b1, 1'b0, 1'b0, 1'b0, (funct == add) ? 3'b010 : (funct == sub?3'b110 : 3'b011)};
        beq:    {pcSrc, regWrite, regDst, memWrite, mem2Reg, aluSrcB, aluControl} = {eq, 1'b0, 1'b0, 1'b0, 1'b0, 1'b0, 3'b010};
        default:{pcSrc, regWrite, regDst, memWrite, mem2Reg, aluSrcB, aluControl} = {1'b0, 1'b0, 1'b0, 1'b0, 1'b0, 1'b0, 3'b010};
    endcase
end

endmodule


// TODO : update the static branch predictor to a 2 bit saturation dynamic one
// now it makes sense why in the ISA we choose distance is from the next instruction preceding the branch instruction, because
// the static branch predictor is used and the next instruction is already fetched and PC is pointing at it while beq is at decode.

mips.v
`include "data_path.v"
`include "control_unit.v"
`include "hazard_unit.v"
module mips(input clk, rst);

    wire [5 : 0] funct, opcode;
    wire         eq, regWrite, regWriteEH, regWriteMH, regWriteDH,
                 regDst, memWrite, mem2RegEH, aluSrcB, pcSrc, flush,
                 mem2RegEE, enableE, enableD, flushD;
    wire [2 : 0] aluControl;
    wire [1 : 0] fad, fbd;
    wire [4 : 0] rsDH, rtDH, rdEH, rdMH;

    controlUnit cu(.eq(eq), .regWrite(regWrite), .regDst(regDst),
                   .memWrite(memWrite), .mem2Reg(mem2Reg), .aluSrcB(aluSrcB), 
                   .pcSrc(pcSrc), .aluControl(aluControl), .opcode(opcode),
                   .funct(funct));

    hazardUnit hu(.eq(eq), .regWriteEH(regWriteEH), .regWriteDH(regWriteDH), 
                  .mem2RegEH(mem2RegEH), .regWriteMH(regWriteMH), .opcode(opcode), 
                  .rsDH(rsDH), .rtDH(rtDH), .rdEH(rdEH), .rdMH(rdMH), .flushD(flushD), 
                  .enableE(enableE), .fad(fad), .fbd(fbd), .enableD(enableD));

    dataPath    dp(.rst(rst), .clk(clk), .regWrite(regWrite), .regDst(regDst),
                   .memWrite(memWrite), .mem2Reg(mem2Reg), .aluSrcB(aluSrcB), 
                   .pcSrc(pcSrc), .aluControl(aluControl), .fad(fad), .fbd(fbd),
                   .enableE(enableE), .rsDH(rsDH), .rtDH(rtDH), .rdEH(rdEH), .rdMH(rdMH),
                   .opcode(opcode), .funct(funct), .eq(eq), .mem2RegEH(mem2RegEH), 
                   .regWriteMH(regWriteMH), .regWriteEH(regWriteEH),.regWriteDH(regWriteDH),
                   .flushD(flushD), .enableD(enableD));

    
endmodule

mips_testbench.v
`include "mips.v"
`timescale 1ns/1ps

module tb;


    reg clk, rst;
    always #10 clk ^= 1;

    mips m(.clk(clk), .rst(rst));

    initial begin
        $dumpfile("mips_testbench.vcd");
        $dumpvars(0, tb);

        clk = 0;
        rst = 1;
        #5;
        rst = 0;

        #10000;
        $finish;
    end


endmodule

mips_testbench.vcd
$date
	Tue Jul 16 11:59:23 2024
$end
$version
	Icarus Verilog
$end
$timescale
	1ps
$end
$scope module tb $end
$var reg 1 ! clk $end
$var reg 1 " rst $end
$scope module m $end
$var wire 1 ! clk $end
$var wire 1 " rst $end
$var wire 5 # rtDH [4:0] $end
$var wire 5 $ rsDH [4:0] $end
$var wire 1 % regWriteMH $end
$var wire 1 & regWriteEH $end
$var wire 1 ' regWriteDH $end
$var wire 1 ( regWrite $end
$var wire 1 ) regDst $end
$var wire 5 * rdMH [4:0] $end
$var wire 5 + rdEH [4:0] $end
$var wire 1 , pcSrc $end
$var wire 6 - opcode [5:0] $end
$var wire 1 . memWrite $end
$var wire 1 / mem2RegEH $end
$var wire 1 0 mem2Reg $end
$var wire 6 1 funct [5:0] $end
$var wire 1 2 flushD $end
$var wire 2 3 fbd [1:0] $end
$var wire 2 4 fad [1:0] $end
$var wire 1 5 eq $end
$var wire 1 6 enableE $end
$var wire 1 7 enableD $end
$var wire 1 8 aluSrcB $end
$var wire 3 9 aluControl [2:0] $end
$scope module cu $end
$var wire 6 : opcode [5:0] $end
$var wire 6 ; funct [5:0] $end
$var wire 1 5 eq $end
$var parameter 6 < add $end
$var parameter 6 = beq $end
$var parameter 6 > lw $end
$var parameter 6 ? rType $end
$var parameter 6 @ sub $end
$var parameter 6 A sw $end
$var reg 3 B aluControl [2:0] $end
$var reg 1 8 aluSrcB $end
$var reg 1 0 mem2Reg $end
$var reg 1 . memWrite $end
$var reg 1 , pcSrc $end
$var reg 1 ) regDst $end
$var reg 1 ( regWrite $end
$upscope $end
$scope module dp $end
$var wire 3 C aluControl [2:0] $end
$var wire 1 8 aluSrcB $end
$var wire 1 ! clk $end
$var wire 32 D immShiftedD [31:0] $end
$var wire 1 0 mem2Reg $end
$var wire 1 / mem2RegEH $end
$var wire 1 . memWrite $end
$var wire 1 , pcSrc $end
$var wire 5 E rdEH [4:0] $end
$var wire 5 F rdMH [4:0] $end
$var wire 1 ) regDst $end
$var wire 1 ( regWrite $end
$var wire 1 ' regWriteDH $end
$var wire 1 % regWriteMH $end
$var wire 5 G rsDH [4:0] $end
$var wire 1 " rst $end
$var wire 5 H rtDH [4:0] $end
$var wire 5 I writeRegE [4:0] $end
$var wire 32 J writeRegData [31:0] $end
$var wire 32 K rtDataD [31:0] $end
$var wire 5 L rtD [4:0] $end
$var wire 32 M rsDataD [31:0] $end
$var wire 5 N rsD [4:0] $end
$var wire 1 & regWriteEH $end
$var wire 5 O rdD [4:0] $end
$var wire 32 P operand2 [31:0] $end
$var wire 1 Q opcodeD $end
$var wire 6 R opcode [5:0] $end
$var wire 32 S memDataM [31:0] $end
$var wire 32 T instr [31:0] $end
$var wire 32 U immD [31:0] $end
$var wire 6 V funct [5:0] $end
$var wire 1 2 flushD $end
$var wire 2 W fbd [1:0] $end
$var wire 2 X fad [1:0] $end
$var wire 1 5 eq $end
$var wire 1 6 enableE $end
$var wire 1 7 enableD $end
$var wire 32 Y aluOutE [31:0] $end
$var reg 32 Z PC [31:0] $end
$var reg 3 [ aluControlE [2:0] $end
$var reg 32 \ aluOutM [31:0] $end
$var reg 32 ] aluOutWB [31:0] $end
$var reg 1 ^ aluSrcBE $end
$var reg 32 _ immE [31:0] $end
$var reg 32 ` instrD [31:0] $end
$var reg 1 / mem2RegE $end
$var reg 1 a mem2RegM $end
$var reg 1 b mem2RegWB $end
$var reg 32 c memDataWB [31:0] $end
$var reg 1 d memWriteE $end
$var reg 1 e memWriteM $end
$var reg 6 f rdE [5:0] $end
$var reg 1 g regDstE $end
$var reg 1 h regWriteE $end
$var reg 1 & regWriteM $end
$var reg 1 i regWriteWB $end
$var reg 32 j rsDataE [31:0] $end
$var reg 32 k rsDataFD [31:0] $end
$var reg 6 l rsE [5:0] $end
$var reg 32 m rtDataE [31:0] $end
$var reg 32 n rtDataFD [31:0] $end
$var reg 32 o rtDataM [31:0] $end
$var reg 6 p rtE [5:0] $end
$var reg 5 q writeRegM [4:0] $end
$var reg 5 r writeRegWB [4:0] $end
$scope module DM $end
$var wire 32 s address [31:0] $end
$var wire 1 ! clk $end
$var wire 32 t dataOutput [31:0] $end
$var wire 32 u dataWrite [31:0] $end
$var wire 1 " rst $end
$var wire 1 e writeEnable $end
$upscope $end
$scope module IM $end
$var wire 32 v address [31:0] $end
$var wire 1 ! clk $end
$var wire 32 w instruction [31:0] $end
$var wire 1 " rst $end
$var integer 32 x i [31:0] $end
$upscope $end
$scope module RF $end
$var wire 32 y accumlator [31:0] $end
$var wire 5 z addressA [4:0] $end
$var wire 5 { addressB [4:0] $end
$var wire 5 | addressWrite [4:0] $end
$var wire 1 ! clk $end
$var wire 32 } const2 [31:0] $end
$var wire 32 ~ const64 [31:0] $end
$var wire 32 !" dataWrite [31:0] $end
$var wire 1 " rst $end
$var wire 1 i writeEnable $end
$var wire 32 "" xored [31:0] $end
$var reg 32 #" dataA [31:0] $end
$var reg 32 $" dataB [31:0] $end
$var integer 32 %" i [31:0] $end
$upscope $end
$scope module a $end
$var wire 3 &" ALUControl [2:0] $end
$var wire 32 '" SrcA [31:0] $end
$var wire 32 (" SrcB [31:0] $end
$var parameter 3 )" add $end
$var parameter 3 *" andd $end
$var parameter 3 +" orr $end
$var parameter 3 ," slt $end
$var parameter 3 -" sub $end
$var parameter 3 ." xorr $end
$var reg 32 /" ALUResult [31:0] $end
$upscope $end
$upscope $end
$scope module hu $end
$var wire 1 7 enableD $end
$var wire 1 6 enableE $end
$var wire 1 5 eq $end
$var wire 1 2 flushD $end
$var wire 1 / mem2RegEH $end
$var wire 6 0" opcode [5:0] $end
$var wire 5 1" rdEH [4:0] $end
$var wire 5 2" rdMH [4:0] $end
$var wire 1 ' regWriteDH $end
$var wire 1 & regWriteEH $end
$var wire 1 % regWriteMH $end
$var wire 5 3" rsDH [4:0] $end
$var wire 5 4" rtDH [4:0] $end
$var parameter 6 5" beq $end
$var reg 2 6" fad [1:0] $end
$var reg 2 7" fbd [1:0] $end
$upscope $end
$upscope $end
$upscope $end
$enddefinitions $end
$comment Show the parameter values. $end
$dumpall
b100 5"
b11 ."
b110 -"
b111 ,"
b1 +"
b0 *"
b10 )"
b101011 A
b100010 @
b0 ?
b100011 >
b100 =
b100000 <
$end
#0
$dumpvars
b0 7"
b0 6"
b0 4"
b0 3"
bx 2"
bx 1"
b0 0"
bx /"
bx ("
bx '"
bx &"
b100000 %"
b0 $"
b0 #"
b0 ""
bx !"
b0 ~
b0 }
bx |
b0 {
b0 z
b0 y
b10000000000 x
b10001100000010100000000000100000 w
b0 v
bx u
bx t
bx s
bx r
bx q
bx p
bx o
b0 n
bx m
bx l
b0 k
bx j
xi
0h
xg
bx f
xe
0d
bx c
xb
xa
b0 `
bx _
x^
bx ]
bx \
bx [
b0 Z
bx Y
b0 X
b0 W
b0 V
b0 U
b10001100000010100000000000100000 T
bx S
b0 R
0Q
bx P
b0 O
b0 N
b0 M
b0 L
b0 K
bx J
bx I
b0 H
b0 G
bx F
bx E
b0 D
b11 C
b11 B
b0 ;
b0 :
b11 9
08
x7
x6
15
b0 4
b0 3
02
b0 1
00
x/
0.
b0 -
0,
bx +
bx *
1)
1(
1'
x&
0%
b0 $
b0 #
1"
0!
$end
#5000
0"
#10000
06
07
0e
0&
b10001100000010110000000000100001 T
b10001100000010110000000000100001 w
b1 Z
b1 v
1!
#20000
0!
#30000
1Q
0)
10
18
b10 9
b10 B
b10 C
b0 +
b0 E
b0 1"
b0 I
b0 Y
b0 /"
b1011 #
b1011 H
b1011 4"
b1011 L
b1011 {
b100001 D
b100001 U
b100001 1
b100001 ;
b100001 V
b100011 -
b100011 :
b100011 R
b100011 0"
b0 P
b0 ("
b10001100000011000000000000100010 T
b10001100000011000000000000100010 w
b10 Z
b10 v
b10001100000010110000000000100001 `
1%
1h
b11 [
b11 &"
0^
1g
0/
b0 f
b0 p
b0 l
b0 _
b0 m
b0 j
b0 '"
0i
1!
#40000
0!
#50000
x5
b1011 +
b1011 E
b1011 1"
b1011 I
06
07
bx k
b100001 Y
b100001 /"
b100001 P
b100001 ("
b10 4
b10 X
b10 6"
b1100 #
b1100 H
b1100 4"
b1100 L
b1100 {
b100010 D
b100010 U
b100010 1
b100010 ;
b100010 V
0a
1&
b0 *
b0 F
b0 2"
b0 q
b0 o
b0 u
b0 \
b0 s
b10 [
b10 &"
1^
0g
1/
b1011 p
b100001 _
b10001100000011000000000000100010 `
b10001100000011010000000000100011 T
b10001100000011010000000000100011 w
b11 Z
b11 v
1!
#60000
0!
#70000
15
b1100 +
b1100 E
b1100 1"
b1100 I
b1101 #
b1101 H
b1101 4"
b1101 L
b1101 {
b100011 D
b100011 U
b100011 1
b100011 ;
b100011 V
b100010 P
b100010 ("
bx Y
bx /"
b0 4
b0 X
b0 6"
b0 k
b0 J
b0 !"
b10000000011010000000000000011 T
b10000000011010000000000000011 w
b100 Z
b100 v
b10001100000011010000000000100011 `
b1100 p
b100010 _
bx j
bx '"
1a
b1011 *
b1011 F
b1011 2"
b1011 q
b0 S
b0 t
b100001 \
b100001 s
0b
b0 r
b0 |
b0 ]
1i
1!
#80000
0!
#90000
05
b100011 n
16
17
b1 3
b1 W
b1 7"
b1101 +
b1101 E
b1101 1"
b1101 I
0Q
02
0,
0'
0(
00
08
b100011 P
b100011 ("
b100011 Y
b100011 /"
b11 D
b11 U
b11 1
b11 ;
b11 V
b100 -
b100 :
b100 R
b100 0"
1b
b1011 r
b1011 |
b100001 ]
b0 c
b1100 *
b1100 F
b1100 2"
b1100 q
bx S
bx t
bx \
bx s
b1101 p
b100011 _
b0 j
b0 '"
b10000000011010000000000000011 `
b1010010110101100000100000 T
b1010010110101100000100000 w
b101 Z
b101 v
1!
#100000
0!
#110000
bx J
bx !"
b1100010110110100000100110 T
b1100010110110100000100110 w
b110 Z
b110 v
b1101 *
b1101 F
b1101 2"
b1101 q
b100 S
b100 t
b100011 \
b100011 s
b1100 r
b1100 |
bx ]
bx c
1!
#120000
bx ~
0!
#130000
b100 J
b100 !"
b1101 r
b1101 |
b100011 ]
b100 c
b10000000000001111111111111100 T
b10000000000001111111111111100 w
b111 Z
b111 v
1!
#140000
b100 K
b100 $"
b100 ""
0!
#150000
b0 T
b0 w
b1000 Z
b1000 v
1!
#160000
0!
#170000
b1001 Z
b1001 v
1!
#180000
0!
#190000
b1010 Z
b1010 v
1!
#200000
0!
#210000
b1011 Z
b1011 v
1!
#220000
0!
#230000
b1100 Z
b1100 v
1!
#240000
0!
#250000
b1101 Z
b1101 v
1!
#260000
0!
#270000
b1110 Z
b1110 v
1!
#280000
0!
#290000
b1111 Z
b1111 v
1!
#300000
0!
#310000
b10000 Z
b10000 v
1!
#320000
0!
#330000
b10001 Z
b10001 v
1!
#340000
0!
#350000
b10010 Z
b10010 v
1!
#360000
0!
#370000
b10011 Z
b10011 v
1!
#380000
0!
#390000
b10100 Z
b10100 v
1!
#400000
0!
#410000
b10101 Z
b10101 v
1!
#420000
0!
#430000
b10110 Z
b10110 v
1!
#440000
0!
#450000
b10111 Z
b10111 v
1!
#460000
0!
#470000
b11000 Z
b11000 v
1!
#480000
0!
#490000
b11001 Z
b11001 v
1!
#500000
0!
#510000
b11010 Z
b11010 v
1!
#520000
0!
#530000
b11011 Z
b11011 v
1!
#540000
0!
#550000
b11100 Z
b11100 v
1!
#560000
0!
#570000
b11101 Z
b11101 v
1!
#580000
0!
#590000
b11110 Z
b11110 v
1!
#600000
0!
#610000
b11111 Z
b11111 v
1!
#620000
0!
#630000
b100000 Z
b100000 v
1!
#640000
0!
#650000
b100001 Z
b100001 v
1!
#660000
0!
#670000
b100010 Z
b100010 v
1!
#680000
0!
#690000
b100011 Z
b100011 v
1!
#700000
0!
#710000
b100100 Z
b100100 v
1!
#720000
0!
#730000
b100101 Z
b100101 v
1!
#740000
0!
#750000
b100110 Z
b100110 v
1!
#760000
0!
#770000
b100111 Z
b100111 v
1!
#780000
0!
#790000
b101000 Z
b101000 v
1!
#800000
0!
#810000
b101001 Z
b101001 v
1!
#820000
0!
#830000
b101010 Z
b101010 v
1!
#840000
0!
#850000
b101011 Z
b101011 v
1!
#860000
0!
#870000
b101100 Z
b101100 v
1!
#880000
0!
#890000
b101101 Z
b101101 v
1!
#900000
0!
#910000
b101110 Z
b101110 v
1!
#920000
0!
#930000
b101111 Z
b101111 v
1!
#940000
0!
#950000
b110000 Z
b110000 v
1!
#960000
0!
#970000
b110001 Z
b110001 v
1!
#980000
0!
#990000
b110010 Z
b110010 v
1!
#1000000
0!
#1010000
b110011 Z
b110011 v
1!
#1020000
0!
#1030000
b110100 Z
b110100 v
1!
#1040000
0!
#1050000
b110101 Z
b110101 v
1!
#1060000
0!
#1070000
b110110 Z
b110110 v
1!
#1080000
0!
#1090000
b110111 Z
b110111 v
1!
#1100000
0!
#1110000
b111000 Z
b111000 v
1!
#1120000
0!
#1130000
b111001 Z
b111001 v
1!
#1140000
0!
#1150000
b111010 Z
b111010 v
1!
#1160000
0!
#1170000
b111011 Z
b111011 v
1!
#1180000
0!
#1190000
b111100 Z
b111100 v
1!
#1200000
0!
#1210000
b111101 Z
b111101 v
1!
#1220000
0!
#1230000
b111110 Z
b111110 v
1!
#1240000
0!
#1250000
b111111 Z
b111111 v
1!
#1260000
0!
#1270000
b1000000 Z
b1000000 v
1!
#1280000
0!
#1290000
b1000001 Z
b1000001 v
1!
#1300000
0!
#1310000
b1000010 Z
b1000010 v
1!
#1320000
0!
#1330000
b1000011 Z
b1000011 v
1!
#1340000
0!
#1350000
b1000100 Z
b1000100 v
1!
#1360000
0!
#1370000
b1000101 Z
b1000101 v
1!
#1380000
0!
#1390000
b1000110 Z
b1000110 v
1!
#1400000
0!
#1410000
b1000111 Z
b1000111 v
1!
#1420000
0!
#1430000
b1001000 Z
b1001000 v
1!
#1440000
0!
#1450000
b1001001 Z
b1001001 v
1!
#1460000
0!
#1470000
b1001010 Z
b1001010 v
1!
#1480000
0!
#1490000
b1001011 Z
b1001011 v
1!
#1500000
0!
#1510000
b1001100 Z
b1001100 v
1!
#1520000
0!
#1530000
b1001101 Z
b1001101 v
1!
#1540000
0!
#1550000
b1001110 Z
b1001110 v
1!
#1560000
0!
#1570000
b1001111 Z
b1001111 v
1!
#1580000
0!
#1590000
b1010000 Z
b1010000 v
1!
#1600000
0!
#1610000
b1010001 Z
b1010001 v
1!
#1620000
0!
#1630000
b1010010 Z
b1010010 v
1!
#1640000
0!
#1650000
b1010011 Z
b1010011 v
1!
#1660000
0!
#1670000
b1010100 Z
b1010100 v
1!
#1680000
0!
#1690000
b1010101 Z
b1010101 v
1!
#1700000
0!
#1710000
b1010110 Z
b1010110 v
1!
#1720000
0!
#1730000
b1010111 Z
b1010111 v
1!
#1740000
0!
#1750000
b1011000 Z
b1011000 v
1!
#1760000
0!
#1770000
b1011001 Z
b1011001 v
1!
#1780000
0!
#1790000
b1011010 Z
b1011010 v
1!
#1800000
0!
#1810000
b1011011 Z
b1011011 v
1!
#1820000
0!
#1830000
b1011100 Z
b1011100 v
1!
#1840000
0!
#1850000
b1011101 Z
b1011101 v
1!
#1860000
0!
#1870000
b1011110 Z
b1011110 v
1!
#1880000
0!
#1890000
b1011111 Z
b1011111 v
1!
#1900000
0!
#1910000
b1100000 Z
b1100000 v
1!
#1920000
0!
#1930000
b1100001 Z
b1100001 v
1!
#1940000
0!
#1950000
b1100010 Z
b1100010 v
1!
#1960000
0!
#1970000
b1100011 Z
b1100011 v
1!
#1980000
0!
#1990000
b1100100 Z
b1100100 v
1!
#2000000
0!
#2010000
b1100101 Z
b1100101 v
1!
#2020000
0!
#2030000
b1100110 Z
b1100110 v
1!
#2040000
0!
#2050000
b1100111 Z
b1100111 v
1!
#2060000
0!
#2070000
b1101000 Z
b1101000 v
1!
#2080000
0!
#2090000
b1101001 Z
b1101001 v
1!
#2100000
0!
#2110000
b1101010 Z
b1101010 v
1!
#2120000
0!
#2130000
b1101011 Z
b1101011 v
1!
#2140000
0!
#2150000
b1101100 Z
b1101100 v
1!
#2160000
0!
#2170000
b1101101 Z
b1101101 v
1!
#2180000
0!
#2190000
b1101110 Z
b1101110 v
1!
#2200000
0!
#2210000
b1101111 Z
b1101111 v
1!
#2220000
0!
#2230000
b1110000 Z
b1110000 v
1!
#2240000
0!
#2250000
b1110001 Z
b1110001 v
1!
#2260000
0!
#2270000
b1110010 Z
b1110010 v
1!
#2280000
0!
#2290000
b1110011 Z
b1110011 v
1!
#2300000
0!
#2310000
b1110100 Z
b1110100 v
1!
#2320000
0!
#2330000
b1110101 Z
b1110101 v
1!
#2340000
0!
#2350000
b1110110 Z
b1110110 v
1!
#2360000
0!
#2370000
b1110111 Z
b1110111 v
1!
#2380000
0!
#2390000
b1111000 Z
b1111000 v
1!
#2400000
0!
#2410000
b1111001 Z
b1111001 v
1!
#2420000
0!
#2430000
b1111010 Z
b1111010 v
1!
#2440000
0!
#2450000
b1111011 Z
b1111011 v
1!
#2460000
0!
#2470000
b1111100 Z
b1111100 v
1!
#2480000
0!
